Workbook

Sheet Indicators_2022
A1: Column1 | B1: Time | C1: Time Code | D1: Country Name | E1: Country Code | F1: Population, total [SP.POP.TOTL] | G1: Population growth (annual %) [SP.POP.GROW] | H1: Surface area (sq. km) [AG.SRF.TOTL.K2] | I1: Poverty headcount ratio at national poverty lines (% of population) [SI.POV.NAHC] | J1: GNI, Atlas method (current US$) [NY.GNP.ATLS.CD] | K1: GNI per capita, Atlas method (current US$) [NY.GNP.PCAP.CD] | L1: GNI, PPP (current international $) [NY.GNP.MKTP.PP.CD] | M1: GNI per capita, PPP (current international $) [NY.GNP.PCAP.PP.CD] | N1: Income share held by lowest 20% [SI.DST.FRST.20] | O1: Life expectancy at birth, total (years) [SP.DYN.LE00.IN] | P1: Fertility rate, total (births per woman) [SP.DYN.TFRT.IN] | Q1: Adolescent fertility rate (births per 1,000 women ages 15-19) [SP.ADO.TFRT] | R1: Contraceptive prevalence, any method (% of married women ages 15-49) [SP.DYN.CONU.ZS] | S1: Births attended by skilled health staff (% of total) [SH.STA.BRTC.ZS] | T1: Mortality rate, under-5 (per 1,000 live births) [SH.DYN.MORT] | U1: Prevalence of underweight, weight for age (% of children under 5) [SH.STA.MALN.ZS] | V1: Immunization, measles (% of children ages 12-23 months) [SH.IMM.MEAS] | W1: Primary completion rate, total (% of relevant age group) [SE.PRM.CMPT.ZS] | X1: School enrollment, secondary (% gross) [SE.SEC.ENRR] | Y1: School enrollment, primary and secondary (gross), gender parity index (GPI) [SE.ENR.PRSC.FM.ZS] | Z1: Prevalence of HIV, total (% of population ages 15-49) [SH.DYN.AIDS.ZS] | AA1: Forest area (sq. km) [AG.LND.FRST.K2] | AB1: Water productivity, total (constant 2015 US$ GDP per cubic meter of total freshwater withdrawal) [ER.GDP.FWTL.M3.KD] | AC1: Energy use (kg of oil equivalent per capita) [EG.USE.PCAP.KG.OE] | AD1: Electric power consumption (kWh per capita) [EG.USE.ELEC.KH.PC] | AE1: GDP (current US$) [NY.GDP.MKTP.CD] | AF1: GDP growth (annual %) [NY.GDP.MKTP.KD.ZG] | AG1: Inflation, GDP deflator (annual %) [NY.GDP.DEFL.KD.ZG] | AH1: Agriculture, forestry, and fishing, value added (% of GDP) [NV.AGR.TOTL.ZS] | AI1: Industry (including construction), value added (% of GDP) [NV.IND.TOTL.ZS] | AJ1: Exports of goods and services (% of GDP) [NE.EXP.GNFS.ZS] | AK1: Imports of goods and services (% of GDP) [NE.IMP.GNFS.ZS] | AL1: Gross capital formation (% of GDP) [NE.GDI.TOTL.ZS] | AM1: Revenue, excluding grants (% of GDP) [GC.REV.XGRT.GD.ZS] | AN1: Market capitalization of listed domestic companies (% of GDP) [CM.MKT.LCAP.GD.ZS] | AO1: Military expenditure (% of GDP) [MS.MIL.XPND.GD.ZS] | AP1: Mobile cellular subscriptions (per 100 people) [IT.CEL.SETS.P2] | AQ1: High-technology exports (% of manufactured exports) [TX.VAL.TECH.MF.ZS] | AR1: Merchandise trade (% of GDP) [TG.VAL.TOTL.GD.ZS] | AS1: Net barter terms of trade index (2015 = 100) [TT.PRI.MRCH.XD.WD] | AT1: External debt stocks, total (DOD, current US$) [DT.DOD.DECT.CD] | AU1: Total debt service (% of GNI) [DT.TDS.DECT.GN.ZS] | AV1: Net migration [SM.POP.NETM] | AW1: Personal remittances, paid (current US$) [BM.TRF.PWKR.CD.DT] | AX1: Foreign direct investment, net inflows (BoP, current US$) [BX.KLT.DINV.CD.WD] | AY1: Net ODA received per capita (current US$) [DT.ODA.ODAT.PC.ZS] | AZ1: GDP per capita (current US$) [NY.GDP.PCAP.CD] | BA1: Foreign direct investment, net (BoP, current US$) [BN.KLT.DINV.CD] | BB1: Inflation, consumer prices (annual %) [FP.CPI.TOTL.ZG]
A2: 0 | B2: 2022 | C2: YR2022 | D2: Afghanistan | E2: AFG | F2: 40578842 | G2: 1.4357044 | H2: 652860 | J2: 1.4887595e+10 | K2: 370 | L2: 8.6404554e+10 | M2: 2130 | O2: 65.617 | P2: 4.932 | Q2: 65.339 | T2: 57.4 | U2: 18.4 | V2: 56 | Z2: 0.1 | AA2: 12084.4 | AB2: 0.75560762 | AE2: 1.4497244e+10 | AF2: -6.240172 | AG2: 9.4062393 | AH2: 33.701432 | AI2: 16.050368 | AJ2: 18.380042 | AK2: 54.505427 | AL2: 16.7 | AP2: 56.2655 | AR2: 32.068164 | AS2: 96.1 | AT2: 3.3932472e+09 | AU2: 0.18280878 | AV2: -647402 | AX2: 0 | AY2: 96.478038 | AZ2: 357.26115 | BB2: 13.712102
A3: 1 | B3: 2022 | C3: YR2022 | D3: Albania | E3: ALB | F3: 2451636 | G3: -1.5431567 | H3: 28750 | I3: 19.7 | J3: 1.8934768e+10 | K3: 7720 | L3: 5.3075778e+10 | M3: 21650 | O3: 78.769 | P3: 1.355 | Q3: 12.827 | T3: 9.4 | V3: 86 | W3: 101.17628 | X3: 97.322471 | Z3: 0.1 | AA3: 7889 | AB3: 18.049366 | AC3: 884.57222 | AD3: 2840.9601 | AE3: 1.9017247e+10 | AF3: 4.8268006 | AG3: 9.8616099 | AH3: 16.984475 | AI3: 23.025052 | AJ3: 37.197076 | AK3: 47.500968 | AL3: 26.802365 | AM3: 24.731661 | AO3: 1.2087886 | AP3: 98.395 | AQ3: 0.059640998 | AR3: 66.823552 | AS3: 115.8 | AT3: 1.0420148e+10 | AU3: 3.77623 | AV3: -16426 | AW3: 1.4948965e+08 | AX3: 1.4413819e+09 | AY3: 129.20652 | AZ3: 7756.9619 | BA3: -1.2498485e+09 | BB3: 6.7252027
A4: 2 | B4: 2022 | C4: YR2022 | D4: Algeria | E4: DZA | F4: 45477389 | G4: 1.5875821 | H4: 2381740 | J4: 2.0143949e+11 | K4: 4430 | L4: 7.0339254e+11 | M4: 15470 | O4: 76.129 | P4: 2.817 | Q4: 8.977 | T4: 22.3 | V4: 79 | W4: 93.929104 | X4: 104.55027 | Z4: 0.1 | AA4: 19680 | AB4: 20.080693 | AC4: 1499.51 | AD4: 1756.5872 | AE4: 2.2558164e+11 | AF4: 3.6 | AG4: 22.920306 | AH4: 10.647064 | AI4: 43.052131 | AJ4: 30.791556 | AK4: 20.398533 | AL4: 35.097954 | AO4: 4.0574881 | AP4: 107.787 | AR4: 46.362815 | AS4: 150.8 | AT4: 7.1292587e+09 | AU4: 0.13590795 | AV4: -14684 | AW4: 77927357 | AX4: 2.4179603e+08 | AY4: 4.7574499 | AZ4: 4960.3033 | BA4: -1.5720979e+08 | BB4: 9.2655155
A5: 3 | B5: 2022 | C5: YR2022 | D5: American Samoa | E5: ASM | F5: 48342 | G5: -1.8100877 | H5: 200 | O5: 72.752 | P5: 2.305 | Q5: 34.104 | AA5: 170.7 | AE5: 871000000 | AF5: 1.7350158 | AG5: 14.152765 | AJ5: 46.95752 | AK5: 77.726751 | AR5: 117.68083 | AS5: 181.8 | AV5: -1305 | AZ5: 18017.459
A6: 4 | B6: 2022 | C6: YR2022 | D6: Andorra | E6: AND | F6: 79705 | G6: 1.6967681 | H6: 470 | J6: 3.7936073e+09 | K6: 47600 | L6: 5.6922481e+09 | M6: 71420 | O6: 84.016 | P6: 1.071 | Q6: 3.527 | T6: 2.7 | V6: 98 | X6: 98.509872 | AA6: 160 | AE6: 3.3806117e+09 | AF6: 9.5646123 | AG6: 4.2366523 | AH6: 0.48749186 | AI6: 11.145341 | AM6: 29.381625 | AP6: 142.426 | AQ6: 13.307661 | AR6: 66.556002 | AS6: 92 | AV6: 1102 | AW6: 1.2388326e+08 | AX6: 5.9398142e+08 | AZ6: 42414.048 | BA6: -4.5060358e+08
A7: 5 | B7: 2022 | C7: YR2022 | D7: Angola | E7: AGO | F7: 35635029 | G7: 3.1430261 | H7: 1246700 | J7: 8.3435815e+10 | K7: 2340 | L7: 3.2081202e+11 | M7: 9000 | O7: 64.246 | P7: 5.209 | Q7: 141.978 | T7: 66.4 | V7: 50 | Z7: 1.6 | AA7: 654972.51 | AB7: 144.46414 | AC7: 423.12252 | AD7: 392.50705 | AE7: 1.3121221e+11 | AF7: 4.2160026 | AG7: 18.121772 | AH7: 18.989093 | AI7: 34.933359 | AJ7: 35.196053 | AK7: 20.05872 | AL7: 14.176986 | AM7: 26.016294 | AO7: 1.4101637 | AP7: 66.6008 | AQ7: 22.063504 | AR7: 52.646016 | AS7: 167.3 | AT7: 6.0445748e+10 | AU7: 12.402875 | AV7: -995 | AW7: 5.1766819e+08 | AX7: -6.5986527e+09 | AY7: 2.6920665 | AZ7: 3682.1132 | BA7: 6.639719e+09 | BB7: 21.35529
A8: 6 | B8: 2022 | C8: YR2022 | D8: Antigua and Barbuda | E8: ATG | F8: 92840 | G8: 0.53027032 | H8: 440 | J8: 1.7475498e+09 | K8: 18820 | L8: 2.6410557e+09 | M8: 28450 | O8: 77.483 | P8: 1.58 | Q8: 33.469 | T8: 9.6 | V8: 99 | W8: 123.35474 | X8: 107.79991 | Z8: 1.1 | AA8: 79.911 | AB8: 368.34 | AE8: 1.8665667e+09 | AF8: 9.1078062 | AG8: 6.7802747 | AH8: 1.9556603 | AI8: 19.658196 | AJ8: 54.723765 | AK8: 62.979763 | AP8: 200.541 | AQ8: 0 | AR8: 45.109559 | AS8: 80.1 | AV8: 0 | AW8: 55995755 | AX8: 3.1327009e+08 | AZ8: 20105.199 | BA8: -3.0382857e+08 | BB8: 7.5310783
A9: 7 | B9: 2022 | C9: YR2022 | D9: Argentina | E9: ARG | F9: 45407904 | G9: 0.21080873 | H9: 2780400 | I9: 39.2 | J9: 5.3979698e+11 | K9: 11890 | L9: 1.3286385e+12 | M9: 29260 | N9: 5.4 | O9: 75.806 | P9: 1.482 | Q9: 25.767 | T9: 9.8 | V9: 85 | W9: 100.31015 | X9: 114.14812 | Z9: 0.4 | AA9: 283550 | AB9: 15.995562 | AC9: 1808.7602 | AD9: 2833.1191 | AE9: 6.3399376e+11 | AF9: 6.0207454 | AG9: 68.993827 | AH9: 6.5415694 | AI9: 24.111864 | AJ9: 16.281668 | AK9: 15.298512 | AL9: 17.385586 | AM9: 17.893195 | AN9: 8.351475 | AO9: 0.68458641 | AP9: 131.484 | AQ9: 4.7515752 | AR9: 26.884019 | AS9: 114.2 | AT9: 248976650822 | AU9: 5.4479512 | AV9: 5589 | AW9: 5.8477318e+08 | AX9: 1.5206087e+10 | AY9: 8.4863981 | AZ9: 13962.189 | BA9: -1.3116251e+10 | BB9: 72.430758
A10: 8 | B10: 2022 | C10: YR2022 | D10: Armenia | E10: ARM | F10: 2969200 | G10: 0.23265626 | H10: 29740 | I10: 24.8 | J10: 1.6893971e+10 | K10: 5690 | L10: 5.5469245e+10 | M10: 18680 | N10: 9.2 | O10: 74.765854 | P10: 1.7 | Q10: 13.487 | T10: 10.5 | V10: 95 | W10: 93.824828 | X10: 91.710661 | Z10: 0.3 | AA10: 3280.5 | AB10: 4.6306808 | AC10: 1347.5906 | AD10: 2403.6778 | AE10: 1.9513507e+10 | AF10: 12.6 | AG10: 7.9858785 | AH10: 10.146704 | AI10: 25.437097 | AJ10: 51.57092 | AK10: 52.307709 | AL10: 22.255132 | AM10: 23.456418 | AN10: 1.2948467 | AO10: 4.081746 | AP10: 130.54 | AQ10: 21.847528 | AR10: 72.406259 | AS10: 98.6 | AT10: 1.5931153e+10 | AU10: 10.463451 | AV10: 38001 | AW10: 6.6633964e+08 | AX10: 9.7565891e+08 | AY10: 101.4859 | AZ10: 6571.9745 | BA10: -9.2591397e+08 | BB10: 8.6409111
A11: 9 | B11: 2022 | C11: YR2022 | D11: Aruba | E11: ABW | F11: 107310 | G11: -0.36277422 | H11: 180 | J11: 3.2362969e+09 | K11: 30160 | L11: 4.3130739e+09 | M11: 40190 | O11: 76.226 | P11: 1.615 | Q11: 18.768 | W11: 93.832939 | X11: 131.80217 | AA11: 4.2 | AE11: 3.3240344e+09 | AF11: 10.636431 | AG11: 4.2890599 | AH11: 0.034214432 | AI11: 9.7359174 | AJ11: 80.806881 | AK11: 79.827665 | AL11: 19.808067 | AP11: 130.648 | AQ11: 7.1251465 | AR11: 47.743188 | AS11: 72.9 | AV11: 152 | AW11: 1.1036104e+08 | AX11: 2.4815028e+08 | AZ11: 30975.999 | BA11: -1.2469428e+08
A12: 10 | B12: 2022 | C12: YR2022 | D12: Australia | E12: AUS | F12: 26018721 | G12: 1.2893113 | H12: 7741220 | J12: 1.5817646e+12 | K12: 60790 | L12: 1.6511382e+12 | M12: 63460 | O12: 83.2 | P12: 1.63 | Q12: 6.747 | T12: 3.7 | V12: 96 | X12: 133.27727 | Z12: 0.1 | AA12: 1340051 | AB12: 137.03594 | AC12: 4942.1637 | AD12: 9923.4317 | AE12: 1.6956275e+12 | AF12: 4.2530456 | AG12: 7.1995443 | AH12: 2.672427 | AI12: 27.401962 | AJ12: 25.46153 | AK12: 20.233112 | AL12: 23.699796 | AM12: 26.131348 | AN12: 99.029527 | AO12: 1.8832971 | AP12: 109.469 | AQ12: 25.83187 | AR12: 42.572557 | AS12: 181 | AV12: 140972 | AW12: 6.5305289e+09 | AX12: 6.870942e+10 | AZ12: 65169.519 | BA12: 5.8640231e+10 | BB12: 6.5940967
A13: 11 | B13: 2022 | C13: YR2022 | D13: Austria | E13: AUT | F13: 9041851 | G13: 0.9562878 | H13: 83879 | J13: 5.0917613e+11 | K13: 56310 | L13: 6.4245136e+11 | M13: 71050 | N13: 7.8 | O13: 81.295122 | P13: 1.41 | Q13: 4.205 | T13: 3.2 | V13: 95 | W13: 97.159172 | X13: 101.458 | AA13: 38954.5 | AB13: 136.29705 | AC13: 3486.7294 | AD13: 8256.6059 | AE13: 4.732213e+11 | AF13: 5.3309638 | AG13: 5.0234316 | AH13: 1.346496 | AI13: 25.844468 | AJ13: 61.427312 | AK13: 62.152267 | AL13: 29.236794 | AM13: 44.264983 | AN13: 26.002211 | AO13: 0.76670601 | AP13: 121.166 | AQ13: 14.91417 | AR13: 94.131012 | AS13: 94 | AV13: 157365 | AW13: 6.9496747e+09 | AX13: 1.4301504e+10 | AZ13: 52336.773 | BA13: 1.123624e+08 | BB13: 8.5468699
A14: 12 | B14: 2022 | C14: YR2022 | D14: Azerbaijan | E14: AZE | F14: 10141756 | G14: 0.039507866 | H14: 86600 | J14: 5.7455095e+10 | K14: 5670 | L14: 2.1337998e+11 | M14: 21040 | O14: 74.125 | P14: 1.67 | Q14: 35.293 | T14: 19.4 | V14: 71 | W14: 99.703281 | X14: 90.953036 | Z14: 0.1 | AA14: 11548.256 | AB14: 4.3593788 | AC14: 1714.0373 | AD14: 2365.8625 | AE14: 7.8807471e+10 | AF14: 4.7146803 | AG14: 37.270721 | AH14: 4.6122083 | AI14: 56.146737 | AJ14: 59.986848 | AK14: 26.995425 | AL14: 12.003714 | AM14: 38.448421 | AN14: 1.8627422 | AO14: 3.7953703 | AP14: 107.506 | AQ14: 3.9129442 | AR14: 66.855337 | AS14: 173.3 | AT14: 1.545749e+10 | AU14: 2.1831177 | AV14: 9086 | AW14: 811938000 | AX14: -4474481000 | AY14: 4.7819302 | AZ14: 7770.5942 | BA14: 4646691000 | BB14: 13.852259
A15: 13 | B15: 2022 | C15: YR2022 | D15: Bahamas, The | E15: BHS | F15: 397538 | G15: 0.29348399 | H15: 13880 | J15: 1.3432451e+10 | K15: 33790 | L15: 1.3834311e+10 | M15: 34800 | O15: 74.491 | P15: 1.379 | Q15: 24.679 | T15: 12.9 | V15: 80 | Z15: 1.2 | AA15: 5098.6 | AE15: 13896800000 | AF15: 10.877901 | AG15: 4.1241697 | AH15: 0.41448391 | AI15: 9.5043463 | AJ15: 37.158914 | AK15: 38.824046 | AL15: 23.815555 | AM15: 18.748902 | AP15: 101.624 | AQ15: 0 | AR15: 31.431697 | AS15: 98.9 | AV15: 1001 | AW15: 2.1650792e+08 | AX15: 5.3091395e+08 | AZ15: 34957.161 | BA15: -3.1643019e+08 | BB15: 5.6054063
A16: 14 | B16: 2022 | C16: YR2022 | D16: Bahrain | E16: BHR | F16: 1524693 | G16: 1.3422196 | H16: 790 | J16: 4.3142062e+10 | K16: 28300 | L16: 9.0066506e+10 | M16: 59070 | O16: 80.992 | P16: 1.839 | Q16: 8.122 | T16: 8.4 | V16: 99 | W16: 101.04302 | X16: 103.39322 | Z16: 0.1 | AA16: 7.4 | AB16: 248.06394 | AC16: 10701.793 | AD16: 22689.158 | AE16: 4.6458191e+10 | AF16: 6.1801613 | AG16: 7.1348888 | AH16: 0.24616047 | AI16: 46.389627 | AJ16: 95.961365 | AK16: 71.179876 | AL16: 24.590187 | AN16: 65.138803 | AO16: 3.4233933 | AP16: 139.636 | AQ16: 0.5699592 | AR16: 98.43474 | AS16: 138.4 | AV16: 18975 | AW16: 2.7117021e+09 | AX16: 1.9513298e+09 | AZ16: 30470.522 | BA16: -3457446.8 | BB16: 3.625741
A17: 15 | B17: 2022 | C17: YR2022 | D17: Bangladesh | E17: BGD | F17: 169384897 | G17: 1.0242338 | H17: 147570 | I17: 18.7 | J17: 4.8337079e+11 | K17: 2850 | L17: 1.4881024e+12 | M17: 8790 | N17: 8.8 | O17: 74.265 | P17: 2.179 | Q17: 73.128 | R17: 64 | T17: 30.7 | U17: 21.7 | V17: 96 | W17: 96.616371 | X17: 67.038459 | Z17: 0.1 | AA17: 18834 | AB17: 8.5204775 | AC17: 297.11836 | AD17: 602.67475 | AE17: 4.6013169e+11 | AF17: 7.0998288 | AG17: 5.0490219 | AH17: 11.217601 | AI17: 33.92008 | AJ17: 12.882226 | AK17: 20.897741 | AL17: 32.047276 | AN17: 25.042885 | AO17: 0.99098339 | AP17: 109.867 | AR17: 30.347616 | AS17: 73.9 | AT17: 96944431751 | AU17: 1.4213358 | AV17: -549990 | AW17: 1.3524049e+08 | AX17: 1.634888e+09 | AY17: 30.727604 | AZ17: 2716.4859 | BA17: -1.6032899e+09 | BB17: 7.6969544
A18: 16 | B18: 2022 | C18: YR2022 | D18: Barbados | E18: BRB | F18: 282318 | G18: 0.060588347 | H18: 430 | J18: 6.8599939e+09 | K18: 24300 | L18: 6.1144865e+09 | M18: 21660 | O18: 75.676 | P18: 1.712 | Q18: 45.848 | T18: 10.4 | V18: 85 | W18: 87.064383 | X18: 104.22233 | Z18: 1.1 | AA18: 63 | AB18: 82.569745 | AE18: 6884900000 | AF18: 17.226463 | AG18: -1.2507344 | AH18: 1.4488228 | AI18: 12.813548 | AP18: 114.581 | AQ18: 17.011739 | AR18: 38.475504 | AS18: 92.6 | AV18: -80 | AX18: 200000000 | AZ18: 24387.039
A19: 17 | B19: 2022 | C19: YR2022 | D19: Belarus | E19: BLR | F19: 9228071 | G19: -0.80422843 | H19: 207630 | I19: 3.9 | J19: 6.6525039e+10 | K19: 7210 | L19: 2.5133658e+11 | M19: 27240 | O19: 74.103366 | P19: 1.326 | Q19: 9.903 | T19: 2.6 | V19: 98 | W19: 94.224472 | X19: 99.060203 | AA19: 87966 | AB19: 40.505744 | AC19: 2862.487 | AD19: 3902.7658 | AE19: 7.377518e+10 | AF19: -4.6583959 | AG19: 14.884862 | AH19: 8.0418187 | AI19: 33.029096 | AJ19: 63.051187 | AK19: 56.973021 | AL19: 21.597906 | AM19: 26.072572 | AN19: 3.3840785 | AO19: 1.6486931 | AP19: 128.315 | AR19: 103.73543 | AS19: 105.9 | AT19: 3.9858867e+10 | AU19: 9.6340361 | AV19: -8000 | AW19: 1.6465787e+08 | AX19: 1.6064177e+09 | AY19: 1.9016403 | AZ19: 7994.6481 | BA19: -1.4262189e+09 | BB19: 15.209675
A20: 18 | B20: 2022 | C20: YR2022 | D20: Belgium | E20: BEL | F20: 11680210 | G20: 0.80816535 | H20: 30689 | I20: 12.3 | J20: 6.3461778e+11 | K20: 54330 | L20: 8.0538037e+11 | M20: 68950 | N20: 9.4 | O20: 81.74878 | P20: 1.53 | Q20: 4.372 | T20: 3.7 | V20: 96 | X20: 142.91808 | Z20: 0.2 | AA20: 6893 | AB20: 120.84015 | AC20: 4368.4456 | AD20: 7282.7458 | AE20: 5.9108578e+11 | AF20: 3.956238 | AG20: 6.6990376 | AH20: 0.67143041 | AI20: 20.002116 | AJ20: 94.421345 | AK20: 96.757687 | AL20: 27.286481 | AM20: 37.284947 | AO20: 1.1624655 | AP20: 101.68 | AQ20: 22.817914 | AR20: 209.82775 | AS20: 97.1 | AV20: 118615 | AW20: 8.0094049e+09 | AX20: 1.3136474e+10 | AZ20: 50605.75 | BA20: 2.1118314e+10 | BB20: 9.5975117
A21: 19 | B21: 2022 | C21: YR2022 | D21: Belize | E21: BLZ | F21: 402733 | G21: 1.8512481 | H21: 22970 | J21: 2.7020363e+09 | K21: 6710 | L21: 5.1662031e+09 | M21: 12830 | O21: 72.19 | P21: 1.949 | Q21: 53.404 | T21: 12.8 | V21: 81 | W21: 108.6841 | X21: 87.438167 | Z21: 1.2 | AA21: 12547.3 | AB21: 24.971682 | AE21: 2846604350 | AF21: 9.2505133 | AG21: 7.2868549 | AH21: 7.7485812 | AI21: 15.486834 | AJ21: 52.578787 | AK21: 55.261463 | AL21: 20.191917 | AO21: 0.97917379 | AP21: 67.175 | AQ21: 0.00018155445 | AR21: 66.711062 | AS21: 82.5 | AT21: 1.4711929e+09 | AU21: 2.8338486 | AV21: 5936 | AW21: 41395472 | AX21: 1.4090797e+08 | AY21: 52.175796 | AZ21: 7068.2173 | BA21: -1.3970756e+08 | BB21: 6.2768932
A22: 20 | B22: 2022 | C22: YR2022 | D22: Benin | E22: BEN | F22: 13759501 | G22: 2.5474093 | H22: 114760 | J22: 1.8679223e+10 | K22: 1360 | L22: 5.2513064e+10 | M22: 3820 | O22: 60.475 | P22: 4.634 | Q22: 78.86 | R22: 22.4 | T22: 80.4 | V22: 52 | W22: 61.64175 | X22: 43.56065 | Z22: 0.7 | AA22: 30351.5 | AB22: 128.96851 | AC22: 375.82098 | AD22: 105.30905 | AE22: 1.7425405e+10 | AF22: 6.2529471 | AG22: 4.1389945 | AH22: 26.896679 | AI22: 17.017827 | AJ22: 20.81533 | AK22: 23.566263 | AL22: 31.148372 | AO22: 0.63208749 | AP22: 105.745 | AQ22: 4.2871562 | AR22: 49.542607 | AS22: 113 | AT22: 1.092733e+10 | AU22: 2.9869892 | AV22: -192 | AW22: 1.0273129e+08 | AX22: 3.759889e+08 | AY22: 61.663056 | AZ22: 1266.4271 | BA22: -3.294192e+08 | BB22: 1.3507786
A23: 21 | B23: 2022 | C23: YR2022 | D23: Bermuda | E23: BMU | F23: 64749 | G23: 0.15610875 | H23: 4290 | J23: 8.5596245e+09 | K23: 132200 | L23: 7.1740567e+09 | M23: 110800 | O23: 82.062 | P23: 1.397 | Q23: 1.614 | AA23: 10 | AE23: 7874381000 | AF23: 6.4762257 | AG23: 1.4457935 | AH23: 0.21854416 | AI23: 5.3259043 | AJ23: 50.298849 | AK23: 24.898376 | AL23: 12.536566 | AN23: 2.6287781 | AP23: 105.274 | AQ23: 12.540291 | AR23: 15.569478 | AS23: 127.4 | AV23: 0 | AW23: 1.7191032e+08 | AX23: 5893778.6 | AZ23: 121613.94 | BA23: 14707318
A24: 22 | B24: 2022 | C24: YR2022 | D24: Bhutan | E24: BTN | F24: 780914 | G24: 0.70318392 | H24: 38390 | I24: 12.4 | J24: 2.8107952e+09 | K24: 3600 | L24: 1.1152433e+10 | M24: 14280 | N24: 8.8 | O24: 72.754 | P24: 1.478 | Q24: 9.388 | T24: 23.9 | V24: 97 | X24: 89.982913 | Z24: 0.2 | AA24: 27290 | AB24: 7.7415018 | AE24: 2.8982277e+09 | AF24: 5.2138678 | AG24: 5.7948552 | AH24: 14.671012 | AI24: 31.824845 | AJ24: 25.49884 | AK24: 60.072377 | AL24: 55.778829 | AP24: 95.1298 | AQ24: 0.012217994 | AR24: 77.116093 | AS24: 175.1 | AT24: 3.1602431e+09 | AU24: 4.8076292 | AV24: 291 | AW24: 33684108 | AX24: 8402097.1 | AY24: 249.96493 | AZ24: 3711.3277 | BA24: -8402097.1 | BB24: 5.6391667
A25: 23 | B25: 2022 | C25: YR2022 | D25: Bolivia | E25: BOL | F25: 12077154 | G25: 1.1642591 | H25: 1098580 | I25: 37.7 | J25: 5.0617292e+10 | K25: 4190 | L25: 1.4494448e+11 | M25: 12000 | N25: 5.1 | O25: 67.434 | P25: 2.584 | Q25: 65.76 | T25: 23.9 | V25: 69 | W25: 96.544111 | X25: 90.372934 | Z25: 0.4 | AA25: 504164.44 | AB25: 103.57855 | AC25: 798.29322 | AD25: 859.30841 | AE25: 5.0959082e+10 | AF25: 3.7474178 | AG25: 2.5910028 | AH25: 8.6602848 | AI25: 32.019272 | AJ25: 27.793992 | AK25: 29.730942 | AL25: 18.040802 | AO25: 0.97325089 | AP25: 101.572 | AQ25: 5.5176975 | AR25: 50.668103 | AS25: 80.9 | AT25: 1.5930335e+10 | AU25: 4.8399269 | AV25: -3008 | AW25: 3.1930643e+08 | AX25: 6236980.1 | AY25: 27.799163 | AZ25: 4219.4611 | BA25: -87031313 | BB25: 1.7463287
A26: 24 | B26: 2022 | C26: YR2022 | D26: Bosnia and Herzegovina | E26: BIH | F26: 3204802 | G26: -1.243638 | H26: 51210 | J26: 2.469315e+10 | K26: 7710 | L26: 6.6788549e+10 | M26: 20840 | O26: 76.777 | P26: 1.481 | Q26: 11.089 | T26: 6.2 | V26: 58 | W26: 100.88081 | X26: 87.037399 | AA26: 21879.1 | AB26: 64.984062 | AC26: 2270.7264 | AD26: 3773.088 | AE26: 2.4534664e+10 | AF26: 4.2268133 | AG26: 11.808838 | AH26: 4.8262493 | AI26: 24.663248 | AJ26: 48.307127 | AK26: 61.898157 | AL26: 27.902668 | AM26: 35.874435 | AO26: 0.75202873 | AP26: 118.944 | AQ26: 5.2247492 | AR26: 102.10044 | AS26: 108.4 | AT26: 1.3439998e+10 | AU26: 4.1156869 | AV26: -485 | AW26: 1.0786753e+08 | AX26: 9.2943999e+08 | AY26: 88.949334 | AZ26: 7655.5942 | BA26: -8.487529e+08 | BB26: 14.020844
A27: 25 | B27: 2022 | C27: YR2022 | D27: Botswana | E27: BWA | F27: 2439892 | G27: 1.5884802 | H27: 581730 | J27: 2.0124231e+10 | K27: 8250 | L27: 4.8822958e+10 | M27: 20010 | O27: 68.749 | P27: 2.785 | Q27: 54.585 | T27: 40.7 | V27: 90 | W27: 101.53218 | Z27: 17.4 | AA27: 150181 | AB27: 81.913897 | AC27: 1165.1497 | AD27: 1522.1985 | AE27: 2.0321151e+10 | AF27: 5.4860171 | AG27: 14.617677 | AH27: 1.5797898 | AI27: 37.45713 | AJ27: 43.543612 | AK27: 42.068096 | AL27: 26.791518 | AM27: 29.457238 | AN27: 152.67334 | AO27: 2.5177829 | AP27: 178.205 | AQ27: 0.50238129 | AR27: 81.058402 | AS27: 77.3 | AT27: 2.0027171e+09 | AU27: 0.86873765 | AV27: -7306 | AW27: 2.1183442e+08 | AX27: 7.0962414e+08 | AY27: 37.196502 | AZ27: 8328.7091 | BA27: -6.9950613e+08 | BB27: 11.665567
A28: 26 | B28: 2022 | C28: YR2022 | D28: Brazil | E28: BRA | F28: 210306415 | G28: 0.36018089 | H28: 8510420 | J28: 1.7743067e+12 | K28: 8440 | L28: 4.0590625e+12 | M28: 19300 | N28: 3.6 | O28: 74.872 | P28: 1.629 | Q28: 42.881 | T28: 14.6 | V28: 81 | X28: 106.03119 | Z28: 0.7 | AA28: 4941960 | AB28: 27.958569 | AC28: 1432.7274 | AD28: 2787.7609 | AE28: 1.9519238e+12 | AF28: 3.0166944 | AG28: 8.570282 | AH28: 5.7674749 | AI28: 22.819457 | AJ28: 19.630765 | AK28: 19.185301 | AL28: 18.08822 | AM28: 26.936513 | AN28: 40.699226 | AO28: 1.0524008 | AP28: 101.245 | AQ28: 9.1113463 | AR28: 32.090443 | AS28: 114.5 | AT28: 5.7925785e+11 | AU28: 6.6345692 | AV28: -253639 | AW28: 2.2383832e+09 | AX28: 7.5501039e+10 | AY28: 2.7503402 | AZ28: 9281.3328 | BA28: -4.2146446e+10 | BB28: 9.2801061
A29: 27 | B29: 2022 | C29: YR2022 | D29: British Virgin Islands | E29: VGB | F29: 38319 | G29: 1.3398687 | H29: 150 | O29: 77.177 | P29: 1.025 | Q29: 14.539 | T29: 13.1 | X29: 72.284027 | AA29: 36.2 | AP29: 92.8913 | AS29: 56.8 | AV29: 550 | AX29: 38118551090
A30: 28 | B30: 2022 | C30: YR2022 | D30: Brunei Darussalam | E30: BRN | F30: 455370 | G30: 0.80455427 | H30: 5770 | J30: 1.410178e+10 | K30: 30970 | L30: 3.6424679e+10 | M30: 79990 | O30: 72.917 | P30: 1.764 | Q30: 8.589 | T30: 9.5 | V30: 97 | W30: 105.50711 | X30: 89.851365 | AA30: 3800 | AB30: 141.30911 | AC30: 9537.0516 | AD30: 11197.488 | AE30: 1.6681536e+10 | AF30: -1.6283315 | AG30: 24.236727 | AH30: 1.0961603 | AI30: 67.925585 | AJ30: 86.389357 | AK30: 60.584609 | AL30: 25.851043 | AO30: 2.61193 | AP30: 116.108 | AQ30: 1.0442596 | AR30: 140.35877 | AS30: 135.4 | AV30: 0 | AX30: -2.9016998e+08 | AZ30: 36632.928 | BA30: 2.9016998e+08 | BB30: 3.6822503
A31: 29 | B31: 2022 | C31: YR2022 | D31: Bulgaria | E31: BGR | F31: 6465097 | G31: -0.65067613 | H31: 111000 | I31: 20.6 | J31: 8.4717136e+10 | K31: 13100 | L31: 2.1901231e+11 | M31: 33880 | N31: 6.2 | O31: 74.160976 | P31: 1.78 | Q31: 39.409 | T31: 6.2 | V31: 91 | W31: 95.713913 | X31: 96.672073 | Z31: 0.1 | AA31: 39190 | AB31: 11.399265 | AC31: 2968.6566 | AD31: 5536.4985 | AE31: 9.0506153e+10 | AF31: 4.0838641 | AG31: 15.918454 | AH31: 3.7113641 | AI31: 25.303721 | AJ31: 69.979475 | AK31: 68.865402 | AL31: 22.687585 | AM31: 36.54038 | AN31: 17.351958 | AO31: 1.587075 | AP31: 116.679 | AQ31: 10.382678 | AR31: 119.20074 | AS31: 97 | AT31: 4.7206483e+10 | AU31: 10.911661 | AV31: 26498 | AW31: 188040000 | AX31: 5060860000 | AZ31: 13999.195 | BA31: -3798280000 | BB31: 15.325259
A32: 30 | B32: 2022 | C32: YR2022 | D32: Burkina Faso | E32: BFA | F32: 22509038 | G32: 2.3090715 | H32: 274200 | J32: 1.8839307e+10 | K32: 840 | L32: 5.5682079e+10 | M32: 2470 | O32: 60.7 | P32: 4.275 | Q32: 88.56 | R32: 33.96274 | T32: 79.9 | V32: 88 | W32: 58.29119 | X32: 33.621287 | Z32: 0.6 | AA32: 61164 | AB32: 20.371128 | AC32: 312.92909 | AD32: 131.19175 | AE32: 1.8622421e+10 | AF32: 1.6267326 | AG32: 4.6425844 | AH32: 20.629761 | AI32: 26.043949 | AJ32: 31.218073 | AK32: 36.302217 | AL32: 18.058505 | AM32: 19.87263 | AO32: 2.9816157 | AP32: 119.463 | AQ32: 1.528999 | AR32: 53.816847 | AS32: 97.3 | AT32: 9.905922e+09 | AU32: 6.1741813 | AV32: -24960 | AW32: 1.8515886e+08 | AX32: 6.6973824e+08 | AY32: 61.858041 | AZ32: 827.33084 | BA32: -6.4620835e+08 | BB32: 14.290235
A33: 31 | B33: 2022 | C33: YR2022 | D33: Burundi | E33: BDI | F33: 13321097 | G33: 2.7058501 | H33: 27830 | J33: 3.8208988e+09 | K33: 290 | L33: 1.4767842e+10 | M33: 1110 | O33: 62.882 | P33: 4.98 | Q33: 54.08 | T33: 50.8 | U33: 27.6 | V33: 89 | Z33: 0.9 | AA33: 2796.4 | AB33: 12.535792 | AE33: 4.0361926e+09 | AF33: 2.3177012 | AG33: 15.049386 | AH33: 34.683721 | AI33: 16.933802 | AO33: 2.5985809 | AP33: 56.26 | AQ33: 1.1179241 | AR33: 36.346135 | AS33: 101.7 | AT33: 9.4693043e+08 | AU33: 0.82360391 | AV33: 1995 | AW33: 16594853 | AX33: 25249489 | AY33: 43.134304 | AZ33: 302.99251 | BA33: -23299308 | BB33: 18.800879
A34: 32 | B34: 2022 | C34: YR2022 | D34: Cabo Verde | E34: CPV | F34: 519741 | G34: 0.59668835 | H34: 4030 | J34: 2.3661059e+09 | K34: 4550 | L34: 4.8661605e+09 | M34: 9360 | O34: 75.907 | P34: 1.533 | Q34: 38.673 | T34: 12.1 | V34: 95 | W34: 99.098558 | X34: 96.431594 | Z34: 0.9 | AA34: 463.2 | AB34: 11.604527 | AE34: 2.2470033e+09 | AF34: 15.843676 | AG34: 6.3431904 | AH34: 4.9540487 | AI34: 11.078924 | AJ34: 38.684254 | AK34: 58.309883 | AL34: 21.879431 | AO34: 0.45608101 | AP34: 113.247 | AQ34: 3.47654 | AR34: 85.580647 | AS34: 90 | AT34: 2.4025745e+09 | AU34: 4.7338498 | AV34: -1253 | AW34: 30236846 | AX34: 1.2201553e+08 | AY34: 161.45941 | AZ34: 4323.3136 | BA34: -1.0342526e+08 | BB34: 7.9309293
A35: 33 | B35: 2022 | C35: YR2022 | D35: Cambodia | E35: KHM | F35: 17201724 | G35: 1.3308881 | H35: 181040 | J35: 3.8995461e+10 | K35: 2270 | L35: 1.1440189e+11 | M35: 6650 | O35: 70.528 | P35: 2.616 | Q35: 47.089 | R35: 61.9 | S35: 98.7 | T35: 23.8 | V35: 83 | W35: 87.257242 | X35: 55.134681 | Z35: 0.6 | AA35: 77569.9 | AB35: 15.841294 | AC35: 501.64414 | AD35: 813.23244 | AE35: 3.9994533e+10 | AF35: 5.1299011 | AG35: 3.4889002 | AH35: 16.544086 | AI35: 40.864963 | AJ35: 72.207061 | AK35: 73.666572 | AL35: 34.594526 | AM35: 14.953851 | AO35: 1.5418835 | AP35: 113.392 | AQ35: 6.562226 | AR35: 130.71036 | AS35: 80.9 | AT35: 2.2473751e+10 | AU35: 7.0957763 | AV35: -31350 | AW35: 3.0233623e+08 | AX35: 3.5788313e+09 | AY35: 90.046382 | AZ35: 2325.0305 | BA35: -3.428345e+09 | BB35: 5.3437026
A36: 34 | B36: 2022 | C36: YR2022 | D36: Cameroon | E36: CMR | F36: 27632771 | G36: 2.6290509 | H36: 475440 | J36: 4.574751e+10 | K36: 1660 | L36: 1.3981233e+11 | M36: 5060 | O36: 62.443 | P36: 4.397 | Q36: 108.328 | T36: 69.5 | V36: 68 | W36: 70.436817 | X36: 45.606672 | Z36: 2.8 | AA36: 202284.8 | AB36: 37.033138 | AC36: 384.10486 | AD36: 283.6849 | AE36: 4.4347206e+10 | AF36: 3.736784 | AG36: 6.8310547 | AH36: 16.546164 | AI36: 27.130359 | AJ36: 19.321813 | AK36: 21.964789 | AL36: 19.10744 | AO36: 0.93935295 | AP36: 89.8274 | AQ36: 3.2886471 | AR36: 30.346895 | AS36: 124.4 | AT36: 1.5122663e+10 | AU36: 4.1884174 | AV36: -4798 | AW36: 32278963 | AX36: 9.2568155e+08 | AY36: 42.957077 | AZ36: 1604.8773 | BA36: -8.9833537e+08 | BB36: 6.2476771
A37: 35 | B37: 2022 | C37: YR2022 | D37: Canada | E37: CAN | F37: 38935934 | G37: 1.8039046 | H37: 15634410 | J37: 2.0967552e+12 | K37: 53850 | L37: 2.4406215e+12 | M37: 62680 | O37: 81.245366 | P37: 1.33 | Q37: 4.889 | T37: 5.1 | V37: 92 | X37: 107.47938 | Z37: 0.1 | AA37: 3468541.3 | AB37: 49.22784 | AC37: 7578.0209 | AD37: 14907.078 | AE37: 2.1904111e+12 | AF37: 4.1890363 | AG37: 7.9067621 | AJ37: 33.943191 | AK37: 33.374431 | AL37: 25.318667 | AM37: 18.972304 | AN37: 126.04353 | AO37: 1.1671326 | AP37: 91.2387 | AQ37: 15.148977 | AR37: 54.254291 | AS37: 121.1 | AV37: 459988 | AW37: 1.0423274e+10 | AX37: 5.0229921e+10 | AZ37: 56256.801 | BA37: 3.8444704e+10 | BB37: 6.8028012
A38: 36 | B38: 2022 | C38: YR2022 | D38: Cayman Islands | E38: CYM | F38: 71591 | G38: 2.0932458 | H38: 264 | J38: 5.3017233e+09 | K38: 74060 | L38: 4.6334141e+09 | M38: 64720 | O38: 79.984 | P38: 1.541 | Q38: 11.515 | W38: 97.956577 | X38: 85.601227 | AA38: 126.4 | AE38: 6.6601612e+09 | AF38: 5.7756671 | AG38: 3.8886317 | AH38: 0.4689399 | AI38: 8.0805517 | AP38: 139.315 | AQ38: 56.646705 | AR38: 27.536871 | AS38: 143.2 | AV38: 942 | AW38: 5.3882516e+08 | AX38: -3.1447364e+09 | AZ38: 93030.705 | BA38: 2.377418e+09
A39: 37 | B39: 2022 | C39: YR2022 | D39: Central African Republic | E39: CAF | F39: 5098039 | G39: -0.27543227 | H39: 622980 | J39: 2.6656252e+09 | K39: 520 | L39: 6.538857e+09 | M39: 1280 | O39: 18.818 | P39: 6.023 | Q39: 163.019 | T39: 387.4 | U39: 18.4 | V39: 32 | Z39: 2.7 | AA39: 222430 | AB39: 28.050845 | AE39: 2.3826186e+09 | AF39: 0.45390188 | AG39: 6.0187788 | AH39: 36.21711 | AI39: 21.1573 | AJ39: 12.3005 | AK39: 32.93307 | AL39: 24.32666 | AO39: 1.7108622 | AP39: 38.8218 | AQ39: 37.297405 | AR39: 24.636759 | AS39: 96.5 | AT39: 1.0455113e+09 | AU39: 0.79256819 | AV39: -17430 | AX39: 24047720 | AY39: 134.13358 | AZ39: 467.35983 | BB39: 5.5831674
A40: 38 | B40: 2022 | C40: YR2022 | D40: Chad | E40: TCD | F40: 18455316 | G40: 3.4566891 | H40: 1284000 | I40: 44.8 | J40: 1.7553237e+10 | K40: 950 | L40: 4.7929337e+10 | M40: 2600 | N40: 6.9 | O40: 54.528 | P40: 6.215 | Q40: 136.697 | T40: 104.3 | U40: 18.2 | V40: 54 | Z40: 1 | AA40: 40914.444 | AB40: 18.098675 | AC40: 198.54477 | AD40: 14.467376 | AE40: 1.7828508e+10 | AF40: 4.129699 | AG40: 14.147701 | AH40: 35.227982 | AI40: 33.063605 | AJ40: 31.735344 | AK40: 16.253034 | AL40: 17.971522 | AO40: 2.0442448 | AP40: 65.4378 | AR40: 34.377526 | AS40: 158.6 | AT40: 3.2696582e+09 | AU40: 2.3891098 | AV40: 36670 | AX40: 614018510 | AY40: 38.055124 | AZ40: 966.03647 | BB40: 5.7880269
A41: 39 | B41: 2022 | C41: YR2022 | D41: Channel Islands | E41: CHI | F41: 167215 | G41: 0.28386992 | O41: 81 | P41: 1.37 | Q41: 8.72 | AE41: 1.1308273e+10 | AF41: 5.3419614 | AG41: 7.3583223 | AH41: 0.65038306 | AI41: 8.3830679 | AV41: 820 | AZ41: 67627.142
A42: 40 | B42: 2022 | C42: YR2022 | D42: Chile | E42: CHL | F42: 19553036 | G42: 0.49578959 | H42: 757244.88 | I42: 6.5 | J42: 3.0182543e+11 | K42: 15440 | L42: 5.7315095e+11 | M42: 29310 | N42: 5.9 | O42: 79.176 | P42: 1.255 | Q42: 7.687 | T42: 6.8 | V42: 94 | W42: 100.26938 | X42: 106.06833 | Z42: 0.6 | AA42: 184565.27 | AB42: 7.8963732 | AC42: 2124.6985 | AD42: 4422.4334 | AE42: 3.0122658e+11 | AF42: 2.1539936 | AG42: 7.5601574 | AH42: 3.2346793 | AI42: 31.033047 | AJ42: 35.606628 | AK42: 39.594989 | AL42: 25.798419 | AM42: 26.081243 | AN42: 94.690155 | AO42: 1.5409907 | AP42: 135.114 | AQ42: 6.9367268 | AR42: 67.446904 | AS42: 125 | AV42: 59374 | AW42: 673119195 | AX42: 1.877199e+10 | AZ42: 15405.617 | BA42: -4.7172967e+09 | BB42: 11.643867
A43: 41 | B43: 2022 | C43: YR2022 | D43: China | E43: CHN | F43: 1412175000 | G43: -0.013099501 | H43: 9562910 | J43: 1.859528e+13 | K43: 13170 | L43: 3.225339e+13 | M43: 22840 | N43: 7.3 | O43: 78.202 | P43: 1.034 | Q43: 5.463 | T43: 6.6 | V43: 99 | AA43: 2237370 | AB43: 29.388677 | AC43: 2676.482 | AD43: 6112.1355 | AE43: 1.8316765e+13 | AF43: 3.1341889 | AG43: 1.9342741 | AH43: 7.1478869 | AI43: 37.894527 | AJ43: 20.297732 | AK43: 17.142988 | AL43: 42.355433 | AM43: 14.655961 | AN43: 62.616658 | AO43: 1.6305339 | AP43: 124.195 | AQ43: 27.765061 | AR43: 34.126883 | AS43: 89.5 | AT43: 2.5305023e+12 | AU43: 2.4894329 | AV43: -293846 | AW43: 2.2156036e+10 | AX43: 1.9020379e+11 | AY43: -0.19861428 | AZ43: 12970.606 | BA43: 1.9846372e+10 | BB43: 1.9735756
A44: 42 | B44: 2022 | C44: YR2022 | D44: Colombia | E44: COL | F44: 51737944 | G44: 1.068293 | H44: 1140619.1 | I44: 36.6 | J44: 3.3939556e+11 | K44: 6560 | L44: 1.0337488e+12 | M44: 19980 | N44: 3.2 | O44: 76.508 | P44: 1.663 | Q44: 60.175 | T44: 12.4 | V44: 88 | W44: 97.117104 | X44: 101.57378 | Z44: 0.6 | AA44: 587433.39 | AB44: 14.620762 | AC44: 851.23278 | AD44: 1528.0855 | AE44: 3.4563249e+11 | AF44: 7.3282773 | AG44: 14.925037 | AH44: 8.8315447 | AI44: 26.123002 | AJ44: 20.388368 | AK44: 27.894287 | AL44: 19.787245 | AM44: 25.407471 | AN44: 19.79342 | AO44: 2.7979828 | AP44: 156.195 | AQ44: 8.4018264 | AR44: 38.888705 | AS44: 154.1 | AT44: 1.8449612e+11 | AU44: 8.1542476 | AV44: 183180 | AW44: 4.4951012e+08 | AX44: 1.7182225e+10 | AY44: 36.425053 | AZ44: 6680.4451 | BA44: -1.3798721e+10 | BB44: 10.177231
A45: 43 | B45: 2022 | C45: YR2022 | D45: Comoros | E45: COM | F45: 834188 | G45: 1.9383769 | H45: 1861 | J45: 1.3303844e+09 | K45: 1590 | L45: 3.0542274e+09 | M45: 3660 | O45: 66.481 | P45: 3.935 | Q45: 56.298 | R45: 11.6 | T45: 41.1 | U45: 9.1 | V45: 71 | Z45: 0.1 | AA45: 320.4 | AB45: 114.14813 | AE45: 1.2224855e+09 | AF45: 2.6030103 | AG45: 5.1855534 | AH45: 35.164324 | AI45: 9.6387981 | AJ45: 12.947028 | AK45: 37.441743 | AL45: 13.334794 | AP45: 100.549 | AQ45: 0.30733085 | AR45: 32.883825 | AS45: 64.9 | AT45: 3.6210126e+08 | AU45: 0.39409981 | AV45: -2002 | AW45: 4450271.1 | AX45: 4128667.5 | AY45: 166.61387 | AZ45: 1465.4796 | BA45: -4128667.5 | BB45: 12.532031
A46: 44 | B46: 2022 | C46: YR2022 | D46: Congo, Dem. Rep. | E46: COD | F46: 102396968 | G46: 3.2234019 | H46: 2344860 | J46: 6.2171323e+10 | K46: 610 | L46: 1.5469579e+11 | M46: 1510 | O46: 60.979 | P46: 6.106 | Q46: 108.06 | T46: 75.7 | V46: 56 | Z46: 0.8 | AA46: 1239520 | AB46: 76.919462 | AC46: 390.89991 | AD46: 130.66793 | AE46: 7.0422346e+10 | AF46: 9.3111694 | AG46: 9.9890768 | AH46: 10.337007 | AI46: 41.957389 | AJ46: 40.820325 | AK46: 45.001845 | AL46: 36.68584 | AM46: 13.235247 | AO46: 0.56770722 | AP46: 48.6774 | AQ46: 0.72315868 | AR46: 38.452283 | AS46: 139.1 | AT46: 1.0683388e+10 | AU46: 1.3333618 | AV46: -14991 | AW46: 2.048157e+09 | AX46: 1.4093738e+09 | AY46: 32.127061 | AZ46: 687.73859 | BA46: -1.4093738e+09
A47: 45 | B47: 2022 | C47: YR2022 | D47: Congo, Rep. | E47: COG | F47: 6035104 | G47: 2.396653 | H47: 342000 | J47: 1.3072468e+10 | K47: 2170 | L47: 3.5764084e+10 | M47: 5930 | O47: 65 | P47: 4.215 | Q47: 111.227 | T47: 41.9 | V47: 65 | Z47: 3.2 | AA47: 219160 | AB47: 221.19999 | AC47: 627.58597 | AD47: 458.98132 | AE47: 1.581703e+10 | AF47: 1.4753561 | AG47: 18.260899 | AH47: 8.0419107 | AI47: 49.245552 | AJ47: 63.812147 | AK47: 34.34919 | AL47: 20.979207 | AO47: 1.9079849 | AP47: 93.6259 | AQ47: 4.3272265 | AR47: 79.041387 | AS47: 126.7 | AT47: 7.3299971e+09 | AU47: 9.408377 | AV47: -995 | AX47: 532256250 | AY47: 116.72855 | AZ47: 2620.838 | BB47: 3.0434433
A48: 46 | B48: 2022 | C48: YR2022 | D48: Costa Rica | E48: CRI | F48: 5081765 | G48: 0.42945304 | H48: 51100 | I48: 25.5 | J48: 6.7119511e+10 | K48: 13210 | L48: 1.2232272e+11 | M48: 24070 | N48: 4.5 | O48: 79.316 | P48: 1.335 | Q48: 26.451 | T48: 10.1 | V48: 90 | W48: 93.170792 | X48: 131.90759 | Z48: 0.6 | AA48: 30676.1 | AB48: 20.177919 | AC48: 1009.2152 | AD48: 2142.9562 | AE48: 6.9243626e+10 | AF48: 4.5514918 | AG48: 6.2803851 | AH48: 4.1400736 | AI48: 20.646438 | AJ48: 42.405196 | AK48: 39.822336 | AL48: 17.697334 | AM48: 28.891426 | AN48: 3.223488 | AP48: 154.989 | AQ48: 21.974896 | AR48: 56.730131 | AS48: 87.8 | AV48: 1006 | AW48: 5.6185636e+08 | AX48: 3.6734043e+09 | AY48: 126.19799 | AZ48: 13625.901 | BA48: -3.0600565e+09 | BB48: 8.2747749
A49: 47 | B49: 2022 | C49: YR2022 | D49: Cote d'Ivoire | E49: CIV | F49: 30395002 | G49: 2.5162293 | H49: 322460 | J49: 7.4090312e+10 | K49: 2440 | L49: 1.9761711e+11 | M49: 6500 | O49: 61.562 | P49: 4.349 | Q49: 93.194 | R49: 31.971157 | T49: 69.2 | V49: 62 | W49: 64.667885 | X49: 54.071411 | Z49: 1.9 | AA49: 26109.389 | AB49: 58.255303 | AC49: 471.77542 | AD49: 323.70454 | AE49: 7.0922825e+10 | AF49: 6.3998836 | AG49: 3.0000006 | AH49: 16.584333 | AI49: 23.044542 | AJ49: 24.26736 | AK49: 28.599031 | AL49: 27.485312 | AM49: 12.045585 | AO49: 0.8652269 | AP49: 161.232 | AQ49: 3.5565703 | AR49: 48.387808 | AS49: 80.8 | AT49: 3.1623477e+10 | AU49: 3.359795 | AV49: 26777 | AW49: 1.4282263e+09 | AX49: 1.5991157e+09 | AY49: 64.729479 | AZ49: 2333.3713 | BA49: -1.4316245e+09 | BB49: 5.2335286
A50: 48 | B50: 2022 | C50: YR2022 | D50: Croatia | E50: HRV | F50: 3855641 | G50: -0.60352195 | H50: 88070 | J50: 7.4682851e+10 | K50: 19370 | L50: 1.6114264e+11 | M50: 41790 | N50: 7.9 | O50: 77.57561 | P50: 1.53 | Q50: 6.945 | T50: 4.6 | V50: 90 | W50: 100.28173 | X50: 105.5778 | Z50: 0.1 | AA50: 19441.1 | AB50: 94.364464 | AC50: 2154.9548 | AD50: 4475.5204 | AE50: 7.1196499e+10 | AF50: 7.2944534 | AG50: 8.0099502 | AH50: 3.3932239 | AI50: 20.065771 | AJ50: 59.512045 | AK50: 65.898833 | AL50: 26.227962 | AM50: 38.257415 | AN50: 27.157923 | AO50: 1.8028527 | AP50: 114.677 | AQ50: 12.063854 | AR50: 98.445852 | AS50: 89.8 | AV50: 11681 | AW50: 9.3768235e+08 | AX50: 3.9273909e+09 | AZ50: 18465.541 | BA50: -4.3264323e+09 | BB50: 10.780581
A51: 49 | B51: 2022 | C51: YR2022 | D51: Cuba | E51: CUB | F51: 11059820 | G51: -0.56215128 | H51: 109880 | O51: 77.629 | P51: 1.412 | Q51: 47.767 | R51: 62.1 | T51: 7.9 | V51: 99 | W51: 93.266321 | X51: 103.62715 | Z51: 0.6 | AA51: 32420 | AB51: 12.004517 | AC51: 815.61586 | AD51: 1102.0975 | AF51: 1.7746523 | AG51: 14.092658 | AH51: 0.80067226 | AI51: 23.783236 | AJ51: 40.489628 | AK51: 53.371148 | AL51: 18.294627 | AP51: 68.718 | AQ51: 7.8755891 | AS51: 93.2 | AV51: -23149 | AY51: 12.531084
A52: 50 | B52: 2022 | C52: YR2022 | D52: Curacao | E52: CUW | F52: 153321 | G52: -0.40811203 | H52: 444 | J52: 3.1401102e+09 | K52: 20480 | L52: 4.4837655e+09 | M52: 29240 | O52: 76.729 | P52: 1.3 | Q52: 13.022 | AA52: 0.7 | AC52: 5649.731 | AD52: 5028.6653 | AE52: 3.0751808e+09 | AF52: 6.906 | AG52: 4.9983116 | AH52: 0.26617439 | AI52: 11.189059 | AP52: 92.7325 | AR52: 84.092616 | AV52: 518 | AW52: 1.3205256e+08 | AX52: 1.7561679e+08 | AZ52: 20057.14 | BA52: -1.571709e+08
A53: 51 | B53: 2022 | C53: YR2022 | D53: Cyprus | E53: CYP | F53: 1331370 | G53: 1.0617468 | H53: 9250 | J53: 2.9883039e+10 | K53: 31810 | L53: 4.6589311e+10 | M53: 49590 | N53: 8.7 | O53: 80.434 | P53: 1.393 | Q53: 7.041 | T53: 3.5 | V53: 84 | W53: 99.373451 | X53: 104.00572 | AA53: 1724.9 | AB53: 132.15358 | AC53: 1682.7049 | AD53: 3848.6672 | AE53: 3.1218039e+10 | AF53: 8.273726 | AG53: 6.6205969 | AH53: 1.1860761 | AI53: 10.375047 | AJ53: 104.66609 | AK53: 101.08745 | AL53: 20.595058 | AM53: 38.077747 | AN53: 20.925914 | AO53: 1.7211885 | AP53: 151.241 | AQ53: 17.659598 | AR53: 53.574794 | AS53: 86 | AV53: 9014 | AW53: 9.7996701e+08 | AX53: 53889707 | AZ53: 33231.043 | BA53: -5.4819619e+09 | BB53: 8.395483
A54: 52 | B54: 2022 | C54: YR2022 | D54: Czechia | E54: CZE | F54: 10672118 | G54: 1.5709726 | H54: 78871.47 | J54: 2.9036074e+11 | K54: 27210 | L54: 5.2939577e+11 | M54: 49610 | N54: 9.8 | O54: 78.929268 | P54: 1.64 | Q54: 6.913 | T54: 2.7 | V54: 97 | W54: 103.10996 | X54: 102.93556 | AA54: 26807.1 | AB54: 152.34429 | AC54: 3895.6293 | AD54: 6363.0293 | AE54: 3.0183123e+11 | AF54: 2.8471707 | AG54: 8.6711009 | AH54: 2.0763498 | AI54: 29.218573 | AJ54: 72.409428 | AK54: 71.602066 | AL54: 31.033301 | AM54: 30.221031 | AN54: 9.5447181 | AO54: 1.3269021 | AP54: 128.105 | AQ54: 21.835362 | AR54: 158.59128 | AS54: 95.2 | AV54: 329739 | AW54: 5.6896403e+09 | AX54: 9.1436003e+09 | AZ54: 28282.224 | BA54: -3.4710765e+09 | BB54: 15.100165
A55: 53 | B55: 2022 | C55: YR2022 | D55: Denmark | E55: DNK | F55: 5903037 | G55: 0.78750246 | H55: 42920 | J55: 4.252487e+11 | K55: 72040 | L55: 4.7140638e+11 | M55: 79860 | N55: 9 | O55: 81.304878 | P55: 1.55 | Q55: 1.196 | T55: 3.5 | V55: 95 | W55: 99.88588 | X55: 130.327 | Z55: 0.1 | AA55: 6303.2 | AB55: 373.43726 | AC55: 2580.5432 | AD55: 5847.1597 | AE55: 4.0011431e+11 | AF55: 0.44383261 | AG55: 10.39841 | AH55: 1.0022853 | AI55: 20.668857 | AJ55: 70.755215 | AK55: 61.24061 | AL55: 24.777203 | AM55: 35.951045 | AO55: 1.3615646 | AP55: 126.484 | AQ55: 15.988289 | AR55: 65.207116 | AS55: 94.3 | AV55: 60219 | AW55: 3.8604791e+09 | AX55: 2.762736e+10 | AZ55: 67781.094 | BA55: 1.4049584e+09 | BB55: 7.696567
A56: 54 | B56: 2022 | C56: YR2022 | D56: Djibouti | E56: DJI | F56: 1137096 | G56: 1.4035293 | H56: 23200 | J56: 3.7581516e+09 | K56: 3310 | L56: 7.6722949e+09 | M56: 6750 | O56: 65.54 | P56: 2.653 | Q56: 19.306 | T56: 52.2 | V56: 50 | Z56: 1 | AA56: 59.644 | AB56: 177.13482 | AE56: 3.5628149e+09 | AF56: 5.166537 | AG56: -0.14775859 | AH56: 2.6310179 | AI56: 15.030873 | AJ56: 159.25074 | AK56: 143.03467 | AL56: -10.595742 | AP56: 46.7771 | AQ56: 3.0241774 | AR56: 272.22857 | AS56: 91.9 | AT56: 3.1701331e+09 | AU56: 2.1379309 | AV56: 500 | AW56: 1980632.6 | AX56: 1.8702285e+08 | AY56: 53.518841 | AZ56: 3133.2578 | BA56: -1.8702285e+08 | BB56: 5.1798085
A57: 55 | B57: 2022 | C57: YR2022 | D57: Dominica | E57: DMA | F57: 66826 | G57: -0.56107826 | H57: 750 | J57: 6.5111203e+08 | K57: 9740 | L57: 1.2623534e+09 | M57: 18890 | O57: 71.081 | P57: 1.482 | Q57: 34.275 | T57: 35.1 | V57: 87 | W57: 96.658989 | X57: 105.38759 | Z57: 0.5 | AA57: 478.7 | AB57: 28.704848 | AE57: 6.2306296e+08 | AF57: 10.396808 | AG57: 0.26182368 | AH57: 12.94382 | AI57: 12.606775 | AP57: 85.1899 | AQ57: 27.594663 | AR57: 46.223258 | AS57: 62.2 | AT57: 5.992337e+08 | AU57: 6.102157 | AV57: -202 | AW57: 12217742 | AX57: 16922306 | AY57: 890.6749 | AZ57: 9323.6609 | BA57: -17650168 | BB57: 2.8849023
A58: 56 | B58: 2022 | C58: YR2022 | D58: Dominican Republic | E58: DOM | F58: 11230734 | G58: 0.95962974 | H58: 146839.46 | I58: 27.7 | J58: 1.0273572e+11 | K58: 9150 | L58: 2.6605925e+11 | M58: 23690 | N58: 6.6 | O58: 74.211 | P58: 2.267 | Q58: 53.582 | T58: 32.2 | V58: 85 | W58: 89.488626 | X58: 76.52832 | Z58: 1 | AA58: 21602.8 | AB58: 13.687327 | AC58: 950.47011 | AD58: 1716.8068 | AE58: 1.1347809e+11 | AF58: 5.2379565 | AG58: 9.5512347 | AH58: 4.1537198 | AI58: 30.825543 | AJ58: 22.026187 | AK58: 32.352011 | AL58: 30.670557 | AM58: 16.362322 | AO58: 0.679073 | AP58: 90.376 | AQ58: 6.0187906 | AR58: 39.358259 | AS58: 93.8 | AT58: 4.8289508e+10 | AU58: 3.3913116 | AV58: -35153 | AW58: 954500000 | AX58: 4050000000 | AY58: 32.786326 | AZ58: 10104.245 | BA58: -4098800000 | BB58: 8.8110921
A59: 57 | B59: 2022 | C59: YR2022 | D59: Ecuador | E59: ECU | F59: 17823897 | G59: 0.79672365 | H59: 256370 | I59: 25.2 | J59: 1.1676172e+11 | K59: 6550 | L59: 2.6641302e+11 | M59: 14950 | N59: 4.7 | O59: 76.577 | P59: 1.861 | Q59: 56.981 | T59: 13.2 | V59: 74 | W59: 99.466628 | X59: 94.133531 | Z59: 0.4 | AA59: 123692.9 | AB59: 10.978374 | AC59: 904.73992 | AD59: 1589.2709 | AE59: 116133121000 | AF59: 5.8684235 | AG59: 2.3480684 | AH59: 7.3930399 | AI59: 29.583591 | AJ59: 30.925246 | AK59: 30.955547 | AL59: 22.405905 | AM59: 30.962541 | AO59: 2.2185153 | AP59: 98.1309 | AQ59: 6.7115792 | AR59: 56.579036 | AS59: 114.4 | AT59: 6.0682884e+10 | AU59: 4.6656953 | AV59: -23090 | AW59: 6.3652772e+08 | AX59: 8.820208e+08 | AY59: 21.183939 | AZ59: 6515.5853 | BA59: -8.820208e+08 | BB59: 3.4661697
A60: 58 | B60: 2022 | C60: YR2022 | D60: Egypt, Arab Rep. | E60: EGY | F60: 112618250 | G60: 1.486097 | H60: 1001450 | J60: 4.5513736e+11 | K60: 4040 | L60: 1.9085747e+12 | M60: 16950 | O60: 71.01 | P60: 2.75 | Q60: 41.852 | T60: 18.1 | V60: 96 | Z60: 0.1 | AA60: 449.8 | AB60: 5.8558336 | AC60: 902.48843 | AD60: 1477.9487 | AE60: 4.7674772e+11 | AF60: 6.5878456 | AG60: 10.425789 | AH60: 10.945754 | AI60: 32.711431 | AJ60: 15.087026 | AK60: 21.896079 | AL60: 19.855913 | AN60: 8.1495849 | AO60: 1.014756 | AP60: 90.6795 | AQ60: 3.4020499 | AR60: 30.82343 | AS60: 118.7 | AT60: 1.6311145e+11 | AU60: 3.8891759 | AV60: 13707 | AW60: 395400000 | AX60: 11399900000 | AY60: 51.669288 | AZ60: 4233.3078 | BA60: -11058100000 | BB60: 13.895661
A61: 59 | B61: 2022 | C61: YR2022 | D61: El Salvador | E61: SLV | F61: 6280319 | G61: 0.39146193 | H61: 21040 | I61: 26.6 | J61: 2.958898e+10 | K61: 4710 | L61: 7.002763e+10 | M61: 11150 | N61: 5.6 | O61: 71.969 | P61: 1.785 | Q61: 54.881 | T61: 10.8 | V61: 80 | W61: 79.718625 | X61: 65.226782 | Z61: 0.4 | AA61: 5748.8 | AB61: 14.112202 | AC61: 768.68343 | AD61: 1109.9755 | AE61: 31870120000 | AF61: 2.9546152 | AG61: 6.5845635 | AH61: 4.5587528 | AI61: 23.731947 | AJ61: 32.433483 | AK61: 56.267626 | AL61: 24.471574 | AM61: 28.191924 | AO61: 1.4332901 | AP61: 183.249 | AQ61: 7.8500189 | AR61: 76.005362 | AS61: 91.6 | AT61: 2.1188282e+10 | AU61: 11.270756 | AV61: -23255 | AW61: 2.7494441e+08 | AX61: 26235087 | AY61: 112.92955 | AZ61: 5074.6021 | BA61: -1.4321225e+08 | BB61: 7.1986162
A62: 60 | B62: 2022 | C62: YR2022 | D62: Equatorial Guinea | E62: GNQ | F62: 1803545 | G62: 2.5130374 | H62: 28050 | I62: 50.7 | J62: 8.2351685e+09 | K62: 4570 | L62: 2.1344997e+10 | M62: 11840 | N62: 6.4 | O62: 63.355 | P62: 4.17 | Q62: 152.146 | T62: 73.4 | V62: 49 | AA62: 24317 | AB62: 503.19298 | AC62: 1283.9352 | AD62: 744.64457 | AE62: 1.3687643e+10 | AF62: 3.2235083 | AG62: 22.100409 | AH62: 2.489783 | AI62: 56.210999 | AJ62: 52.967085 | AK62: 28.845931 | AL62: 7.3381547 | AM62: 26.449876 | AO62: 1.3031878 | AP62: 49.538 | AR62: 61.712595 | AS62: 195.7 | AV62: 3997 | AX62: 1388191640 | AY62: 6.8853568 | AZ62: 7589.2996 | BB62: 4.786717
A63: 61 | B63: 2022 | C63: YR2022 | D63: Eritrea | E63: ERI | F63: 3409447 | G63: 1.7535137 | H63: 121765.8 | O63: 67.789 | P63: 3.786 | Q63: 65.724 | T63: 36.6 | V63: 93 | W63: 61.279419 | X63: 44.044128 | Z63: 0.5 | AA63: 10489.4 | AC63: 289.54779 | AD63: 102.36264 | AP63: 59.1248 | AR63: 37.031677 | AS63: 100.5 | AT63: 7.271077e+08 | AV63: -17134 | AX63: -32045670 | AY63: 18.621045
A64: 62 | B64: 2022 | C64: YR2022 | D64: Estonia | E64: EST | F64: 1348840 | G64: 1.3365515 | H64: 45340 | I64: 22.5 | J64: 3.7197346e+10 | K64: 27580 | L64: 6.295603e+10 | M64: 46670 | N64: 7.7 | O64: 77.843902 | P64: 1.41 | Q64: 5.344 | T64: 2.2 | V64: 87 | W64: 98.522392 | X64: 112.55185 | Z64: 0.8 | AA64: 24384 | AB64: 23.523529 | AC64: 3559.0489 | AD64: 6464.0728 | AE64: 3.8226642e+10 | AF64: -1.2261697 | AG64: 16.844809 | AH64: 2.4464086 | AI64: 23.090768 | AJ64: 87.429938 | AK64: 88.257181 | AL64: 27.727909 | AM64: 35.105164 | AO64: 2.1348521 | AP64: 152.271 | AQ64: 18.018644 | AR64: 129.80999 | AS64: 98.5 | AV64: 39754 | AW64: 3.3242414e+08 | AX64: 1.8778172e+09 | AZ64: 28340.383 | BA64: -1.6468326e+08 | BB64: 19.398263
A65: 63 | B65: 2022 | C65: YR2022 | D65: Eswatini | E65: SWZ | F65: 1218917 | G65: 1.0162074 | H65: 17360 | J65: 4.4535269e+09 | K65: 3650 | L65: 1.1934669e+10 | M65: 9790 | O65: 63.028 | P65: 2.801 | Q65: 69.773 | R65: 57.7 | T65: 46.2 | V65: 83 | W65: 105.5789 | X65: 88.291359 | Z65: 25.2 | AA65: 4999.8 | AB65: 4.2178746 | AC65: 958.91694 | AD65: 1137.075 | AE65: 4.7466603e+09 | AF65: 0.38607084 | AG65: 8.8686547 | AH65: 7.5711696 | AI65: 34.686378 | AJ65: 44.495394 | AK65: 48.076193 | AL65: 22.09256 | AO65: 1.6549953 | AP65: 121.492 | AQ65: 0.31591177 | AR65: 86.692532 | AS65: 81.9 | AT65: 1.2479973e+09 | AU65: 1.9484871 | AV65: -8549 | AW65: 40562436 | AX65: 13350248 | AY65: 80.093592 | AZ65: 3894.162 | BA65: -35061312
A66: 64 | B66: 2022 | C66: YR2022 | D66: Ethiopia | E66: ETH | F66: 125384287 | G66: 2.622695 | H66: 1136239.7 | J66: 1.20562e+11 | K66: 960 | L66: 3.5509443e+11 | M66: 2830 | O66: 66.897 | P66: 4.082 | Q66: 71.137 | T66: 48.2 | V66: 62 | W66: 60.901123 | Z66: 0.8 | AA66: 169225 | AB66: 9.6423945 | AC66: 377.92175 | AD66: 92.435825 | AE66: 123140304666 | AF66: 5.3217599 | AG66: 34.666605 | AH66: 37.642227 | AI66: 22.717527 | AJ66: 8.2439604 | AK66: 18.351539 | AL66: 25.342227 | AM66: 5.0557192 | AO66: 1.5059407 | AP66: 56.9643 | AQ66: 3.2102657 | AR66: 18.379847 | AS66: 100.5 | AT66: 3.0620768e+10 | AU66: 1.6421629 | AV66: -11996 | AW66: 20498639 | AX66: 3.6699913e+09 | AY66: 39.321283 | AZ66: 982.10316 | BA66: -3.6699913e+09 | BB66: 33.88988
A67: 65 | B67: 2022 | C67: YR2022 | D67: Faroe Islands | E67: FRO | F67: 53912 | G67: 1.1491806 | H67: 12960 | J67: 3.9335111e+09 | K67: 72960 | L67: 4.1579994e+09 | M67: 77130 | O67: 82.943902 | P67: 2.0713 | Q67: 4.767 | AA67: 0.8 | AE67: 3.6152418e+09 | AF67: 3.8609998 | AG67: 5.8965035 | AH67: 18.73583 | AI67: 17.731217 | AJ67: 61.374404 | AK67: 61.488938 | AL67: 32.323509 | AP67: 105.804 | AS67: 103.6 | AV67: 614 | AZ67: 67058.202
A68: 66 | B68: 2022 | C68: YR2022 | D68: Fiji | E68: FJI | F68: 919422 | G68: 0.29529473 | H68: 18270 | J68: 4.8295257e+09 | K68: 5250 | L68: 1.1301178e+10 | M68: 12290 | O68: 67.148 | P68: 2.305 | Q68: 21.271 | T68: 28.9 | V68: 99 | W68: 116.08363 | X68: 95.306834 | Z68: 0.7 | AA68: 11533.8 | AB68: 57.304324 | AE68: 4.9778619e+09 | AF68: 17.745127 | AG68: 8.0740527 | AH68: 14.192895 | AI68: 17.793818 | AM68: 20.77071 | AO68: 1.3609077 | AP68: 111.749 | AQ68: 2.2412459 | AR68: 81.40041 | AS68: 89.7 | AT68: 2.9880441e+09 | AU68: 4.0876471 | AV68: -3557 | AW68: 13569841 | AX68: 1.0358159e+08 | AY68: 392.68561 | AZ68: 5414.1209 | BA68: -86910439 | BB68: 4.3201186
A69: 67 | B69: 2022 | C69: YR2022 | D69: Finland | E69: FIN | F69: 5556106 | G69: 0.27194453 | H69: 338470 | I69: 12.2 | J69: 3.0068144e+11 | K69: 54120 | L69: 3.438854e+11 | M69: 61890 | N69: 9.3 | O69: 81.187805 | P69: 1.32 | Q69: 3.221 | T69: 2.3 | V69: 94 | W69: 98.38308 | X69: 144.85246 | AA69: 224090 | AB69: 85.223534 | AC69: 5683.951 | AD69: 14738.2 | AE69: 2.802531e+11 | AF69: 0.76304191 | AG69: 6.1727808 | AH69: 2.2413437 | AI69: 25.180829 | AJ69: 46.28478 | AK69: 48.277754 | AL69: 27.2854 | AM69: 37.181506 | AO69: 1.5885452 | AP69: 128.023 | AQ69: 9.6239284 | AR69: 65.440133 | AS69: 96.5 | AV69: 60353 | AW69: 1.4791173e+09 | AX69: 1.3079164e+10 | AZ69: 50440.56 | BA69: 8.9780384e+09 | BB69: 7.1235077
A70: 68 | B70: 2022 | C70: YR2022 | D70: France | E70: FRA | F70: 68184457 | G70: 0.50232093 | H70: 606410 | J70: 3.1368477e+12 | K70: 46010 | L70: 3.9306369e+12 | M70: 57650 | N70: 7.8 | O70: 82.129268 | P70: 1.79 | Q70: 3.979 | T70: 4.3 | V70: 95 | X70: 104.31644 | Z70: 0.3 | AA70: 174198 | AB70: 108.49242 | AC70: 3100.1898 | AD70: 6649.3893 | AE70: 2.7947881e+12 | AF70: 2.7167626 | AG70: 3.0181842 | AH70: 1.7201714 | AI70: 15.769154 | AJ70: 36.616048 | AK70: 39.346959 | AL70: 24.023352 | AM70: 44.278992 | AO70: 1.9577207 | AP70: 115.951 | AQ70: 22.983183 | AR70: 51.656044 | AS70: 94.8 | AV70: 179377 | AW70: 1.8405718e+10 | AX70: 1.1229548e+11 | AZ70: 40988.64 | BA70: -9.3035831e+09 | BB70: 5.2223675
A71: 69 | B71: 2022 | C71: YR2022 | D71: French Polynesia | E71: PYF | F71: 280378 | G71: 0.20922228 | H71: 3471 | J71: 6.7700823e+09 | K71: 24150 | O71: 83.859 | P71: 1.515 | Q71: 24.725 | AA71: 1494.6 | AE71: 5.6226883e+09 | AF71: 2.9373471 | AG71: 2.48931 | AJ71: 21.817122 | AK71: 47.709281 | AL71: 22.506743 | AP71: 116.866 | AQ71: 9.9820964 | AR71: 41.385897 | AS71: 89.3 | AV71: -1348 | AX71: -9480300 | AZ71: 20053.957
A72: 70 | B72: 2022 | C72: YR2022 | D72: Gabon | E72: GAB | F72: 2430747 | G72: 2.247639 | H72: 267670 | J72: 1.8060756e+10 | K72: 7430 | L72: 4.4956865e+10 | M72: 18500 | O72: 67.713 | P72: 3.712 | Q72: 93.319 | T72: 34.1 | V72: 52 | Z72: 3 | AA72: 235068.4 | AB72: 114.06655 | AC72: 2096.2456 | AD72: 1065.1047 | AE72: 2.0440656e+10 | AF72: 3.0376145 | AG72: 14.758343 | AH72: 6.5061694 | AI72: 56.129741 | AJ72: 67.578733 | AK72: 24.484356 | AL72: 16.02694 | AO72: 1.3582461 | AP72: 123.233 | AQ72: 3.9075849 | AR72: 71.083825 | AS72: 135.4 | AT72: 7.9905317e+09 | AU72: 3.0958803 | AV72: 987 | AX72: 1104592040 | AY72: 55.449174 | AZ72: 8409.2074 | BB72: 4.231248
A73: 71 | B73: 2022 | C73: YR2022 | D73: Gambia, The | E73: GMB | F73: 2636470 | G73: 2.3199211 | H73: 11300 | J73: 2.1780258e+09 | K73: 830 | L73: 7.9724532e+09 | M73: 3020 | O73: 64.859 | P73: 4.078 | Q73: 59.158 | T73: 45.6 | V73: 74 | W73: 80.331696 | Z73: 1.4 | AA73: 2312.011 | AB73: 18.441977 | AE73: 2.2047345e+09 | AF73: 5.4929982 | AG73: 8.8170758 | AH73: 22.860439 | AI73: 15.58897 | AJ73: 8.5698506 | AK73: 36.152071 | AL73: 28.623649 | AO73: 0.70592316 | AP73: 106.782 | AQ73: 3.2124882 | AR73: 38.553394 | AS73: 95.6 | AT73: 1.1796061e+09 | AU73: 1.9062547 | AV73: -3000 | AW73: 21148937 | AX73: 231488000 | AY73: 103.32328 | AZ73: 836.24488 | BA73: -231488000 | BB73: 11.51312
A74: 72 | B74: 2022 | C74: YR2022 | D74: Georgia | E74: GEO | F74: 3712502 | G74: 0.10488995 | H74: 69700 | I74: 15.6 | J74: 2.1107767e+10 | K74: 5690 | L74: 7.7588062e+10 | M74: 20900 | N74: 7 | O74: 74.141 | P74: 1.82 | Q74: 21.511 | T74: 9.3 | V74: 90 | W74: 110.7882 | X74: 103.71021 | Z74: 0.4 | AA74: 28224 | AB74: 16.465418 | AC74: 1543.5838 | AD74: 3682.961 | AE74: 2.4984569e+10 | AF74: 10.958532 | AG74: 8.1354501 | AH74: 6.6323552 | AI74: 21.32978 | AJ74: 52.478879 | AK74: 62.216558 | AL74: 24.066663 | AM74: 26.489157 | AO74: 1.6078768 | AP74: 154.014 | AQ74: 2.9492009 | AR74: 76.539243 | AS74: 95.3 | AT74: 2.331953e+10 | AU74: 13.294833 | AV74: 26999 | AW74: 2.9032555e+08 | AX74: 2.2577369e+09 | AY74: 101.49529 | AZ74: 6729.8466 | BA74: -1.8925654e+09 | BB74: 11.898165
A75: 73 | B75: 2022 | C75: YR2022 | D75: Germany | E75: DEU | F75: 83177813 | G75: -0.02195657 | H75: 357600 | J75: 4.5913093e+12 | K75: 55200 | L75: 5.8691683e+12 | M75: 70560 | O75: 80.608049 | P75: 1.455 | Q75: 5.577 | T75: 3.7 | V75: 96 | W75: 97.758423 | X75: 100.8173 | Z75: 0.1 | AA75: 114190 | AB75: 144.52965 | AC75: 3261.8564 | AD75: 6316.2757 | AE75: 4.2010217e+12 | AF75: 1.8092581 | AG75: 6.4131591 | AH75: 0.99463828 | AI75: 25.560349 | AJ75: 45.628404 | AK75: 43.15735 | AL75: 23.276015 | AM75: 28.500974 | AN75: 44.981056 | AO75: 1.3503051 | AP75: 124.158 | AQ75: 17.498151 | AR75: 77.602336 | AS75: 96.2 | AV75: 981552 | AW75: 2.224197e+10 | AX75: 8.7215415e+10 | AZ75: 50506.518 | BA75: 6.370205e+10 | BB75: 6.8725744
A76: 74 | B76: 2022 | C76: YR2022 | D76: Ghana | E76: GHA | F76: 33149152 | G76: 1.9202903 | H76: 238533 | J76: 7.9506151e+10 | K76: 2400 | L76: 2.3484484e+11 | M76: 7080 | O76: 65.246 | P76: 3.434 | Q76: 58.808 | R76: 36.3 | T76: 38.5 | U76: 12 | V76: 95 | W76: 93.415525 | X76: 77.81687 | Z76: 1.6 | AA76: 80001.611 | AB76: 47.305139 | AC76: 359.17938 | AD76: 552.50282 | AE76: 7.3919003e+10 | AF76: 3.8048498 | AG76: 28.183873 | AH76: 19.513638 | AI76: 31.470051 | AJ76: 34.664044 | AK76: 35.451412 | AL76: 16.407852 | AM76: 15.550551 | AN76: 8.7442467 | AO76: 0.33794636 | AP76: 120.803 | AQ76: 1.9574072 | AR76: 43.151285 | AS76: 111.1 | AT76: 4.3607006e+10 | AU76: 8.0631172 | AV76: -10003 | AW76: 7.4077919e+08 | AX76: 1.4284117e+09 | AY76: 31.669495 | AZ76: 2229.8912 | BA76: -1.4725696e+09 | BB76: 31.255895
A77: 75 | B77: 2022 | C77: YR2022 | D77: Gibraltar | E77: GIB | F77: 37609 | G77: 2.0170692 | H77: 10 | O77: 83.517 | P77: 1.895 | Q77: 8.477 | W77: 106.04027 | X77: 72.422279 | AA77: 0 | AC77: 6522.235 | AD77: 5424.2336 | AP77: 97.6043 | AS77: 83.6 | AV77: 613
A78: 76 | B78: 2022 | C78: YR2022 | D78: Greece | E78: GRC | F78: 10436882 | G78: -1.2598895 | H78: 131960 | J78: 2.2940209e+11 | K78: 21980 | L78: 4.0139908e+11 | M78: 38460 | N78: 7.2 | O78: 80.787805 | P78: 1.32 | Q78: 6.941 | T78: 3.8 | V78: 94 | W78: 99.349899 | X78: 106.21671 | Z78: 0.3 | AA78: 39018 | AB78: 21.349872 | AC78: 1957.7987 | AD78: 4827.7829 | AE78: 2.1799019e+11 | AF78: 5.5219858 | AG78: 6.2854124 | AH78: 3.7849073 | AI78: 16.720114 | AJ78: 49.231621 | AK78: 58.890223 | AL78: 18.809411 | AM78: 45.242068 | AN78: 27.081622 | AO78: 4.0003525 | AP78: 109.027 | AQ78: 14.470865 | AR78: 72.392707 | AS78: 93.3 | AV78: -53997 | AW78: 2.9373235e+09 | AX78: 8.0579702e+09 | AZ78: 20886.524 | BA78: -5.4355363e+09 | BB78: 9.6452598
A79: 77 | B79: 2022 | C79: YR2022 | D79: Greenland | E79: GRL | F79: 56661 | G79: 0.014120056 | H79: 410450 | O79: 71.540488 | P79: 1.818 | Q79: 36.42 | AA79: 2.2 | AE79: 3.1523348e+09 | AF79: 2.0045558 | AG79: 5.6064967 | AH79: 16.025894 | AI79: 19.511889 | AJ79: 40.790087 | AK79: 52.575046 | AL79: 37.840709 | AP79: 118.637 | AR79: 61.097572 | AS79: 89.6 | AV79: -323 | AZ79: 55635.001
A80: 78 | B80: 2022 | C80: YR2022 | D80: Grenada | E80: GRD | F80: 116913 | G80: 0.19263622 | H80: 340 | J80: 1.1672795e+09 | K80: 9980 | L80: 1.9080112e+09 | M80: 16320 | O80: 75.151 | P80: 1.502 | Q80: 29.357 | T80: 18.5 | V80: 76 | AA80: 177 | AB80: 77.993354 | AE80: 1.2240074e+09 | AF80: 7.3102381 | AG80: 1.6398519 | AH80: 4.1200428 | AI80: 16.140365 | AP80: 95.7592 | AQ80: 2.1771875 | AR80: 51.143481 | AS80: 77.7 | AT80: 8.5372757e+08 | AU80: 4.6899419 | AV80: -190 | AW80: 51691057 | AX80: 1.62962e+08 | AY80: -800.92459 | AZ80: 10469.387 | BA80: -1.5321204e+08 | BB80: 2.5805393
A81: 79 | B81: 2022 | C81: YR2022 | D81: Guam | E81: GUM | F81: 165180 | G81: 0.88170587 | H81: 540 | O81: 77.102 | P81: 2.819 | Q81: 33.902 | AA81: 280 | AE81: 6910000000 | AF81: 5.0998643 | AG81: 5.4651791 | AJ81: 7.8871201 | AK81: 63.97974 | AR81: 18.422576 | AS81: 112.3 | AV81: -500 | AZ81: 41833.152
A82: 80 | B82: 2022 | C82: YR2022 | D82: Guatemala | E82: GTM | F82: 17847877 | G82: 1.4062371 | H82: 108890 | J82: 9.3112169e+10 | K82: 5220 | L82: 2.2723523e+11 | M82: 12730 | O82: 71.206 | P82: 2.343 | Q82: 69.116 | T82: 22.1 | V82: 86 | W82: 86.545447 | X82: 45.892623 | Z82: 0.2 | AA82: 35046 | AB82: 23.544899 | AC82: 887.83893 | AD82: 669.88359 | AE82: 9.5641447e+10 | AF82: 4.1845182 | AG82: 6.3720535 | AH82: 9.0821014 | AI82: 22.63066 | AJ82: 18.9455 | AK82: 35.485538 | AL82: 16.568532 | AM82: 12.893685 | AO82: 0.46166596 | AP82: 115.156 | AQ82: 4.971624 | AR82: 49.989834 | AS82: 94 | AT82: 2.5269487e+10 | AU82: 4.4252741 | AV82: -8463 | AW82: 23852430 | AX82: 1450072830 | AY82: 24.616656 | AZ82: 5358.7016 | BA82: -719823040 | BB82: 6.8851282
A83: 81 | B83: 2022 | C83: YR2022 | D83: Guinea | E83: GIN | F83: 14055137 | G83: 2.4825041 | H83: 245860 | J83: 1.8059939e+10 | K83: 1280 | L83: 5.6104397e+10 | M83: 3990 | O83: 60.432 | P83: 4.303 | Q83: 120.438 | T83: 97.8 | U83: 15 | V83: 51 | Z83: 1.4 | AA83: 61090 | AB83: 15.594925 | AE83: 1.9910453e+10 | AF83: 3.9724078 | AG83: 2.8055829 | AH83: 28.381974 | AI83: 26.50293 | AJ83: 45.418651 | AK83: 48.746621 | AL83: 14.014222 | AO83: 2.1886572 | AP83: 108.885 | AR83: 68.285741 | AS83: 121.7 | AT83: 4.903692e+09 | AU83: 1.073013 | AV83: -3997 | AW83: 134925700 | AX83: 658300000 | AY83: 35.739603 | AZ83: 1416.5961 | BA83: -650100000 | BB83: 10.493041
A84: 82 | B84: 2022 | C84: YR2022 | D84: Guinea-Bissau | E84: GNB | F84: 2105529 | G84: 2.2423539 | H84: 36130 | J84: 2.0149619e+09 | K84: 960 | L84: 5.9011679e+09 | M84: 2800 | O84: 63.605 | P84: 3.911 | Q84: 83.159 | T84: 71.6 | V84: 75 | Z84: 2.4 | AA84: 19631.3 | AB84: 9.0586009 | AE84: 1.8596014e+09 | AF84: 5.5298725 | AG84: 3.8810408 | AH84: 39.575955 | AI84: 12.680719 | AJ84: 14.724844 | AK84: 31.033652 | AL84: 22.608438 | AM84: 10.689304 | AO84: 1.3982919 | AP84: 125.935 | AR84: 38.395325 | AS84: 93.3 | AT84: 1.2507355e+09 | AU84: 3.4389496 | AV84: -1400 | AW84: 78747312 | AX84: 21658004 | AY84: 71.101492 | AZ84: 883.19913 | BA84: -21122878 | BB84: 9.3907593
A85: 83 | B85: 2022 | C85: YR2022 | D85: Guyana | E85: GUY | F85: 821637 | G85: 0.75193422 | H85: 214970 | J85: 8.0396377e+09 | K85: 9780 | L85: 1.9759668e+10 | M85: 24050 | O85: 69.888 | P85: 2.437 | Q85: 71.313 | T85: 26.6 | V85: 97 | Z85: 1.5 | AA85: 183969.31 | AB85: 9.8760993 | AE85: 1.4718388e+10 | AF85: 63.334634 | AG85: 12.060449 | AH85: 10.029836 | AI85: 67.820642 | AO85: 0.60139423 | AP85: 112.565 | AQ85: 0.12395411 | AR85: 101.26788 | AS85: 156 | AT85: 2.0701084e+09 | AU85: 1.5921119 | AV85: -6161 | AW85: 1.6918448e+08 | AX85: -2.996952e+09 | AY85: 244.00795 | AZ85: 17913.493 | BA85: 3.0016287e+09 | BB85: 6.1150555
A86: 84 | B86: 2022 | C86: YR2022 | D86: Haiti | E86: HTI | F86: 11503606 | G86: 1.1278983 | H86: 27750 | J86: 1.8641006e+10 | K86: 1620 | L86: 3.7723087e+10 | M86: 3280 | O86: 63.948 | P86: 2.699 | Q86: 50.589 | T86: 56.9 | V86: 66 | Z86: 1.7 | AA86: 3410.8 | AB86: 9.9702264 | AC86: 377.52606 | AD86: 74.846096 | AE86: 2.0253552e+10 | AF86: -1.681984 | AG86: 29.784952 | AH86: 20.275349 | AI86: 29.341138 | AJ86: 7.2387601 | AK86: 29.29079 | AL86: 15.862139 | AO86: 0.068740858 | AP86: 65.1889 | AR86: 29.150442 | AS86: 80.2 | AT86: 2.9652701e+09 | AU86: 0.17357379 | AV86: -32220 | AW86: 7.2538629e+08 | AX86: 39413200 | AY86: 78.156237 | AZ86: 1760.6264 | BA86: -39413200 | BB86: 33.983932
A87: 85 | B87: 2022 | C87: YR2022 | D87: Honduras | E87: HND | F87: 10463872 | G87: 1.6767966 | H87: 112490 | J87: 2.8217098e+10 | K87: 2700 | L87: 6.5532094e+10 | M87: 6260 | O87: 72.715 | P87: 2.522 | Q87: 82.781 | T87: 16 | V87: 77 | W87: 68.237843 | X87: 53.86058 | Z87: 0.2 | AA87: 63173.6 | AB87: 16.162833 | AC87: 573.34445 | AD87: 757.08113 | AE87: 3.1426042e+10 | AF87: 4.1435619 | AG87: 9.312395 | AH87: 12.473273 | AI87: 25.908425 | AJ87: 42.439182 | AK87: 70.259343 | AL87: 26.326232 | AO87: 1.465577 | AP87: 75.8551 | AR87: 97.377838 | AS87: 95.2 | AT87: 1.2638567e+10 | AU87: 5.7805824 | AV87: -5374 | AW87: 3.3851906e+08 | AX87: 7.582865e+08 | AY87: 75.256854 | AZ87: 3003.29 | BA87: -7.3773608e+08 | BB87: 9.0896391
A88: 86 | B88: 2022 | C88: YR2022 | D88: Hong Kong SAR, China | E88: HKG | F88: 7346100 | G88: -0.90791452 | H88: 1110 | J88: 3.9666931e+11 | K88: 54000 | L88: 5.3728696e+11 | M88: 73140 | O88: 83.660976 | P88: 0.701 | Q88: 1.13 | W88: 105.85714 | X88: 106.18521 | AC88: 1566.3961 | AD88: 6374.675 | AE88: 3.5867953e+11 | AF88: -3.6837841 | AG88: 1.6886488 | AH88: 0.052901972 | AI88: 6.2626537 | AJ88: 194.48652 | AK88: 190.39463 | AL88: 15.22993 | AN88: 1273.2282 | AP88: 292.808 | AQ88: 72.636773 | AR88: 356.16166 | AS88: 99.9 | AV88: -3427 | AW88: 9.0137091e+08 | AX88: 1.2240791e+11 | AZ88: 48825.844 | BA88: -3.4056946e+09 | BB88: 1.8813671
A89: 87 | B89: 2022 | C89: YR2022 | D89: Hungary | E89: HUN | F89: 9605074 | G89: -0.26885015 | H89: 93030 | J89: 1.8440433e+11 | K89: 19200 | L89: 4.112559e+11 | M89: 42820 | O89: 75.868293 | P89: 1.56 | Q89: 18.766 | T89: 3.9 | V89: 99 | W89: 97.42411 | X89: 102.90858 | AA89: 20500.989 | AB89: 33.73218 | AC89: 2672.8677 | AD89: 4702.931 | AE89: 1.7700258e+11 | AF89: 4.1523806 | AG89: 13.967891 | AH89: 3.1431003 | AI89: 24.233085 | AJ89: 89.771947 | AK89: 95.228257 | AL89: 34.361367 | AM89: 37.944407 | AN89: 13.48399 | AO89: 1.8331482 | AP89: 105.794 | AQ89: 18.404892 | AR89: 178.98496 | AS89: 93.8 | AV89: 41871 | AW89: 1.0745819e+09 | AX89: -1.9173715e+09 | AZ89: 18428.029 | BA89: -4.005856e+09 | BB89: 14.608144
A90: 88 | B90: 2022 | C90: YR2022 | D90: Iceland | E90: ISL | F90: 382003 | G90: 2.5137734 | H90: 103000 | J90: 2.8148068e+10 | K90: 73690 | L90: 2.7827248e+10 | M90: 72850 | O90: 82.119512 | P90: 1.589 | Q90: 3.515 | T90: 2.6 | V90: 91 | W90: 98.945107 | X90: 112.58939 | Z90: 0.1 | AA90: 526.6 | AB90: 75.882756 | AC90: 15806.785 | AD90: 51258.76 | AE90: 2.9166103e+10 | AF90: 8.820694 | AG90: 8.8317495 | AH90: 4.0879859 | AI90: 21.450379 | AJ90: 46.741622 | AK90: 46.307098 | AL90: 24.251135 | AM90: 30.666736 | AP90: 120.115 | AQ90: 33.311629 | AR90: 58.218268 | AS90: 100 | AV90: 6535 | AW90: 4.5695948e+08 | AX90: 1.3825374e+09 | AZ90: 76350.455 | BA90: -1.1346666e+09 | BB90: 8.3087551
A91: 89 | B91: 2022 | C91: YR2022 | D91: India | E91: IND | F91: 1425423212 | G91: 0.79020054 | H91: 3287260 | J91: 3.4048291e+12 | K91: 2390 | L91: 1.2943323e+13 | M91: 9080 | N91: 10.4 | O91: 71.698 | P91: 1.994 | Q91: 14.185 | T91: 29.1 | V91: 95 | X91: 81.655846 | AA91: 726930 | AB91: 4.6190564 | AC91: 727.9022 | AD91: 1085.3352 | AE91: 3.3461073e+12 | AF91: 7.609365 | AG91: 5.8971419 | AH91: 16.54613 | AI91: 25.38452 | AJ91: 23.251541 | AK91: 26.823729 | AL91: 33.619259 | AM91: 9.1101178 | AN91: 101.23306 | AO91: 2.3830981 | AP91: 80.1818 | AQ91: 12.682279 | AR91: 35.081242 | AS91: 81.4 | AT91: 6.155149e+11 | AU91: 1.99103 | AV91: -1353478 | AW91: 1.0088812e+10 | AX91: 4.9940258e+10 | AY91: 1.977003 | AZ91: 2347.4483 | BA91: -3.5408009e+10 | BB91: 6.6990341
A92: 90 | B92: 2022 | C92: YR2022 | D92: Indonesia | E92: IDN | F92: 278830529 | G92: 0.74605047 | H92: 1916906.8 | I92: 9.5 | J92: 1.2615216e+12 | K92: 4520 | L92: 3.8754886e+12 | M92: 13900 | N92: 7.8 | O92: 70.925 | P92: 2.149 | Q92: 26.581 | R92: 52.4 | T92: 21.3 | U92: 16.8 | V92: 92 | W92: 102.06806 | X92: 97.81676 | Z92: 0.4 | AA92: 909221.31 | AB92: 5.0408445 | AC92: 953.65393 | AD92: 1330.9877 | AE92: 1.3191012e+12 | AF92: 5.3071972 | AG92: 9.5689876 | AH92: 12.39965 | AI92: 41.429264 | AJ92: 24.502912 | AK92: 20.961759 | AL92: 29.745314 | AN92: 46.265472 | AO92: 0.7680126 | AP92: 122.873 | AQ92: 8.3081931 | AR92: 40.135359 | AS92: 124.9 | AT92: 3.95986e+11 | AU92: 5.8753142 | AV92: -37501 | AW92: 7.9475678e+09 | AX92: 2.470203e+10 | AY92: 2.3945863 | AZ92: 4730.8348 | BA92: -1.8067208e+10 | BB92: 4.2094646
A93: 91 | B93: 2022 | C93: YR2022 | D93: Iran, Islamic Rep. | E93: IRN | F93: 89524246 | G93: 1.2010029 | H93: 1745150 | J93: 3.9329845e+11 | K93: 4390 | L93: 1.5675207e+12 | M93: 17510 | N93: 7.2 | O93: 76.799 | P93: 1.704 | Q93: 26.291 | T93: 12.2 | V93: 99 | AA93: 107760 | AB93: 5.2638855 | AC93: 3266.1225 | AD93: 3664.2587 | AE93: 4.2266226e+11 | AF93: 4.3528109 | AG93: 51.077656 | AH93: 10.695042 | AI93: 41.218778 | AJ93: 25.566619 | AK93: 23.351732 | AL93: 40.725573 | AN93: 381.63917 | AO93: 2.1106213 | AP93: 162.713 | AQ93: 0.81400792 | AR93: 37.059377 | AS93: 131.8 | AT93: 9.4599555e+09 | AU93: 0.041785029 | AV93: 403190 | AX93: 1500000000 | AY93: 3.2494021 | AZ93: 4721.2044 | BB93: 43.488464
A94: 92 | B94: 2022 | C94: YR2022 | D94: Iraq | E94: IRQ | F94: 44070551 | G94: 2.2936966 | H94: 435050 | J94: 2.427774e+11 | K94: 5510 | L94: 6.3213675e+11 | M94: 14340 | O94: 72.037 | P94: 3.294 | Q94: 58.979 | T94: 23.3 | V94: 97 | Z94: 0.1 | AA94: 8250 | AB94: 4.584306 | AC94: 1411.5887 | AD94: 1373.1165 | AE94: 2.8737223e+11 | AF94: 7.959048 | AG94: 26.941611 | AH94: 2.0587062 | AI94: 65.272125 | AJ94: 44.525946 | AK94: 24.232848 | AL94: 24.31486 | AO94: 1.6400113 | AP94: 99.1324 | AR94: 60.283834 | AS94: 143.5 | AT94: 2.2722727e+10 | AU94: 1.6204506 | AV94: 76821 | AW94: 633000000 | AX94: -2088200000 | AY94: 35.644767 | AZ94: 6520.7315 | BA94: 2326500000 | BB94: 4.994766
A95: 93 | B95: 2022 | C95: YR2022 | D95: Ireland | E95: IRL | F95: 5212836 | G95: 1.9810166 | H95: 70280 | J95: 3.9601088e+11 | K95: 75970 | L95: 4.8556015e+11 | M95: 93150 | N95: 8.9 | O95: 82.509756 | P95: 1.54 | Q95: 4.151 | T95: 3.7 | V95: 90 | W95: 96.469948 | X95: 133.1505 | Z95: 0.2 | AA95: 7900.2 | AB95: 304.7111 | AC95: 2600.1574 | AD95: 6107.0404 | AE95: 5.4834179e+11 | AF95: 7.5111389 | AG95: 8.0040772 | AH95: 1.1728153 | AI95: 40.756448 | AJ95: 139.50598 | AK95: 98.249439 | AL95: 22.884086 | AM95: 21.57008 | AO95: 0.21250238 | AP95: 110.609 | AQ95: 46.78678 | AR95: 65.912357 | AS95: 71.1 | AV95: 93535 | AW95: 2.4005908e+09 | AX95: -3.5575911e+10 | AZ95: 105190.69 | BA95: 2.7133483e+10 | BB95: 7.8294574
A96: 94 | B96: 2022 | C96: YR2022 | D96: Isle of Man | E96: IMN | F96: 84132 | G96: 0.030908594 | H96: 570 | J96: 6.5996834e+09 | K96: 78440 | O96: 80.956 | P96: 1.556 | Q96: 8.827 | AA96: 34.6 | AE96: 7.4312574e+09 | AF96: -4.1653935 | AG96: 9.096475 | AH96: 0.37246678 | AI96: 6.936464 | AV96: 199 | AZ96: 88328.548
A97: 95 | B97: 2022 | C97: YR2022 | D97: Israel | E97: ISR | F97: 9557500 | G97: 1.9663688 | H97: 22070 | J97: 5.2996266e+11 | K97: 55450 | L97: 5.1149355e+11 | M97: 53520 | O97: 82.7 | P97: 2.89 | Q97: 6.737 | T97: 3.4 | V97: 98 | W97: 94.911957 | X97: 96.585373 | AA97: 1400 | AC97: 2501.4206 | AD97: 6842.7936 | AE97: 5.2518101e+11 | AF97: 6.2632634 | AG97: 4.9353036 | AH97: 1.1618337 | AI97: 19.426943 | AJ97: 31.385328 | AK97: 29.259525 | AL97: 27.282152 | AM97: 33.242781 | AN97: 51.341782 | AO97: 4.4330122 | AP97: 151.138 | AQ97: 29.109054 | AR97: 34.436508 | AS97: 91.3 | AV97: 50004 | AW97: 3600600000 | AX97: 22883500000 | AZ97: 54949.622 | BA97: -11928200000 | BB97: 4.4116273
A98: 96 | B98: 2022 | C98: YR2022 | D98: Italy | E98: ITA | F98: 59013667 | G98: -0.20230087 | H98: 302070 | J98: 2.3049638e+12 | K98: 39060 | L98: 3.3501033e+12 | M98: 56770 | N98: 6.8 | O98: 82.7 | P98: 1.24 | Q98: 2.988 | T98: 2.8 | V98: 94 | W98: 97.153458 | X98: 101.35386 | Z98: 0.3 | AA98: 96737.5 | AB98: 59.203875 | AC98: 2411.6517 | AD98: 5215.6901 | AE98: 2.1040676e+12 | AF98: 4.8211767 | AG98: 3.4553592 | AH98: 1.8903718 | AI98: 23.279144 | AJ98: 35.09914 | AK98: 36.917362 | AL98: 24.59773 | AM98: 39.60767 | AO98: 1.6516425 | AP98: 131.674 | AQ98: 9.1591623 | AR98: 64.297458 | AS98: 89.9 | AV98: 231228 | AW98: 1.1587287e+10 | AX98: 6.1897757e+10 | AZ98: 35653.904 | BA98: -1.4640401e+10 | BB98: 8.2012899
A99: 97 | B99: 2022 | C99: YR2022 | D99: Jamaica | E99: JAM | F99: 2839144 | G99: 0.051507657 | H99: 10990 | J99: 1.7994405e+10 | K99: 6340 | L99: 3.3117099e+10 | M99: 11660 | O99: 71.481 | P99: 1.372 | Q99: 36.812 | R99: 60.6 | T99: 19.3 | V99: 91 | X99: 82.858467 | Z99: 1.2 | AA99: 6046.611 | AB99: 12.63759 | AC99: 968.87942 | AD99: 1147.529 | AE99: 1.8813517e+10 | AF99: 6.4393032 | AG99: 12.656897 | AH99: 6.7997968 | AI99: 17.449449 | AN99: 69.382828 | AO99: 1.2899994 | AP99: 105.762 | AQ99: 1.4709848 | AR99: 51.197233 | AS99: 113.3 | AT99: 1.5812061e+10 | AU99: 8.4268768 | AV99: -10003 | AW99: 3.634482e+08 | AX99: 318736000 | AY99: 34.031538 | AZ99: 6626.475 | BA99: -2.58446e+08 | BB99: 10.349569
A100: 98 | B100: 2022 | C100: YR2022 | D100: Japan | E100: JPN | F100: 125124989 | G100: -0.44385192 | H100: 377969.27 | J100: 5.3349169e+12 | K100: 42640 | L100: 6.2963381e+12 | M100: 50320 | O100: 83.996341 | P100: 1.26 | Q100: 1.821 | T100: 2.4 | V100: 98 | X100: 102.33797 | AA100: 249350 | AB100: 56.892354 | AC100: 3129.6586 | AD100: 7800.0806 | AE100: 4.2624633e+12 | AF100: 0.94199878 | AG100: 0.39904897 | AH100: 0.9218813 | AI100: 27.717437 | AJ100: 21.546424 | AK100: 25.266563 | AL100: 26.775574 | AN100: 126.22925 | AO100: 1.009944 | AP100: 168.603 | AQ100: 18.259262 | AR100: 38.569481 | AS100: 79.3 | AV100: 175003 | AW100: 4.5296985e+09 | AX100: 4.8153833e+10 | AZ100: 34065.644 | BA100: 1.2678961e+11 | BB100: 2.4977028
...

Sheet regions
A1: name | B1: alpha-2 | C1: alpha-3 | D1: country-code | E1: iso_3166-2 | F1: region | G1: sub-region | H1: intermediate-region | I1: region-code | J1: sub-region-code | K1: intermediate-region-code
A2: Afghanistan | B2: AF | C2: AFG | D2: 4 | E2: ISO 3166-2:AF | F2: Asia | G2: Southern Asia | I2: 142 | J2: 34
A3: Åland Islands | B3: AX | C3: ALA | D3: 248 | E3: ISO 3166-2:AX | F3: Europe | G3: Northern Europe | I3: 150 | J3: 154
A4: Albania | B4: AL | C4: ALB | D4: 8 | E4: ISO 3166-2:AL | F4: Europe | G4: Southern Europe | I4: 150 | J4: 39
A5: Algeria | B5: DZ | C5: DZA | D5: 12 | E5: ISO 3166-2:DZ | F5: Africa | G5: Northern Africa | I5: 2 | J5: 15
A6: American Samoa | B6: AS | C6: ASM | D6: 16 | E6: ISO 3166-2:AS | F6: Oceania | G6: Polynesia | I6: 9 | J6: 61
A7: Andorra | B7: AD | C7: AND | D7: 20 | E7: ISO 3166-2:AD | F7: Europe | G7: Southern Europe | I7: 150 | J7: 39
A8: Angola | B8: AO | C8: AGO | D8: 24 | E8: ISO 3166-2:AO | F8: Africa | G8: Sub-Saharan Africa | H8: Middle Africa | I8: 2 | J8: 202 | K8: 17
A9: Anguilla | B9: AI | C9: AIA | D9: 660 | E9: ISO 3166-2:AI | F9: Americas | G9: Latin America and the Caribbean | H9: Caribbean | I9: 19 | J9: 419 | K9: 29
A10: Antarctica | B10: AQ | C10: ATA | D10: 10 | E10: ISO 3166-2:AQ
A11: Antigua and Barbuda | B11: AG | C11: ATG | D11: 28 | E11: ISO 3166-2:AG | F11: Americas | G11: Latin America and the Caribbean | H11: Caribbean | I11: 19 | J11: 419 | K11: 29
A12: Argentina | B12: AR | C12: ARG | D12: 32 | E12: ISO 3166-2:AR | F12: Americas | G12: Latin America and the Caribbean | H12: South America | I12: 19 | J12: 419 | K12: 5
A13: Armenia | B13: AM | C13: ARM | D13: 51 | E13: ISO 3166-2:AM | F13: Asia | G13: Western Asia | I13: 142 | J13: 145
A14: Aruba | B14: AW | C14: ABW | D14: 533 | E14: ISO 3166-2:AW | F14: Americas | G14: Latin America and the Caribbean | H14: Caribbean | I14: 19 | J14: 419 | K14: 29
A15: Australia | B15: AU | C15: AUS | D15: 36 | E15: ISO 3166-2:AU | F15: Oceania | G15: Australia and New Zealand | I15: 9 | J15: 53
A16: Austria | B16: AT | C16: AUT | D16: 40 | E16: ISO 3166-2:AT | F16: Europe | G16: Western Europe | I16: 150 | J16: 155
A17: Azerbaijan | B17: AZ | C17: AZE | D17: 31 | E17: ISO 3166-2:AZ | F17: Asia | G17: Western Asia | I17: 142 | J17: 145
A18: Bahamas | B18: BS | C18: BHS | D18: 44 | E18: ISO 3166-2:BS | F18: Americas | G18: Latin America and the Caribbean | H18: Caribbean | I18: 19 | J18: 419 | K18: 29
A19: Bahrain | B19: BH | C19: BHR | D19: 48 | E19: ISO 3166-2:BH | F19: Asia | G19: Western Asia | I19: 142 | J19: 145
A20: Bangladesh | B20: BD | C20: BGD | D20: 50 | E20: ISO 3166-2:BD | F20: Asia | G20: Southern Asia | I20: 142 | J20: 34
A21: Barbados | B21: BB | C21: BRB | D21: 52 | E21: ISO 3166-2:BB | F21: Americas | G21: Latin America and the Caribbean | H21: Caribbean | I21: 19 | J21: 419 | K21: 29
A22: Belarus | B22: BY | C22: BLR | D22: 112 | E22: ISO 3166-2:BY | F22: Europe | G22: Eastern Europe | I22: 150 | J22: 151
A23: Belgium | B23: BE | C23: BEL | D23: 56 | E23: ISO 3166-2:BE | F23: Europe | G23: Western Europe | I23: 150 | J23: 155
A24: Belize | B24: BZ | C24: BLZ | D24: 84 | E24: ISO 3166-2:BZ | F24: Americas | G24: Latin America and the Caribbean | H24: Central America | I24: 19 | J24: 419 | K24: 13
A25: Benin | B25: BJ | C25: BEN | D25: 204 | E25: ISO 3166-2:BJ | F25: Africa | G25: Sub-Saharan Africa | H25: Western Africa | I25: 2 | J25: 202 | K25: 11
A26: Bermuda | B26: BM | C26: BMU | D26: 60 | E26: ISO 3166-2:BM | F26: Americas | G26: Northern America | I26: 19 | J26: 21
A27: Bhutan | B27: BT | C27: BTN | D27: 64 | E27: ISO 3166-2:BT | F27: Asia | G27: Southern Asia | I27: 142 | J27: 34
A28: Bolivia, Plurinational State of | B28: BO | C28: BOL | D28: 68 | E28: ISO 3166-2:BO | F28: Americas | G28: Latin America and the Caribbean | H28: South America | I28: 19 | J28: 419 | K28: 5
A29: Bonaire, Sint Eustatius and Saba | B29: BQ | C29: BES | D29: 535 | E29: ISO 3166-2:BQ | F29: Americas | G29: Latin America and the Caribbean | H29: Caribbean | I29: 19 | J29: 419 | K29: 29
A30: Bosnia and Herzegovina | B30: BA | C30: BIH | D30: 70 | E30: ISO 3166-2:BA | F30: Europe | G30: Southern Europe | I30: 150 | J30: 39
A31: Botswana | B31: BW | C31: BWA | D31: 72 | E31: ISO 3166-2:BW | F31: Africa | G31: Sub-Saharan Africa | H31: Southern Africa | I31: 2 | J31: 202 | K31: 18
A32: Bouvet Island | B32: BV | C32: BVT | D32: 74 | E32: ISO 3166-2:BV | F32: Americas | G32: Latin America and the Caribbean | H32: South America | I32: 19 | J32: 419 | K32: 5
A33: Brazil | B33: BR | C33: BRA | D33: 76 | E33: ISO 3166-2:BR | F33: Americas | G33: Latin America and the Caribbean | H33: South America | I33: 19 | J33: 419 | K33: 5
A34: British Indian Ocean Territory | B34: IO | C34: IOT | D34: 86 | E34: ISO 3166-2:IO | F34: Africa | G34: Sub-Saharan Africa | H34: Eastern Africa | I34: 2 | J34: 202 | K34: 14
A35: Brunei Darussalam | B35: BN | C35: BRN | D35: 96 | E35: ISO 3166-2:BN | F35: Asia | G35: South-eastern Asia | I35: 142 | J35: 35
A36: Bulgaria | B36: BG | C36: BGR | D36: 100 | E36: ISO 3166-2:BG | F36: Europe | G36: Eastern Europe | I36: 150 | J36: 151
A37: Burkina Faso | B37: BF | C37: BFA | D37: 854 | E37: ISO 3166-2:BF | F37: Africa | G37: Sub-Saharan Africa | H37: Western Africa | I37: 2 | J37: 202 | K37: 11
A38: Burundi | B38: BI | C38: BDI | D38: 108 | E38: ISO 3166-2:BI | F38: Africa | G38: Sub-Saharan Africa | H38: Eastern Africa | I38: 2 | J38: 202 | K38: 14
A39: Cabo Verde | B39: CV | C39: CPV | D39: 132 | E39: ISO 3166-2:CV | F39: Africa | G39: Sub-Saharan Africa | H39: Western Africa | I39: 2 | J39: 202 | K39: 11
A40: Cambodia | B40: KH | C40: KHM | D40: 116 | E40: ISO 3166-2:KH | F40: Asia | G40: South-eastern Asia | I40: 142 | J40: 35
A41: Cameroon | B41: CM | C41: CMR | D41: 120 | E41: ISO 3166-2:CM | F41: Africa | G41: Sub-Saharan Africa | H41: Middle Africa | I41: 2 | J41: 202 | K41: 17
A42: Canada | B42: CA | C42: CAN | D42: 124 | E42: ISO 3166-2:CA | F42: Americas | G42: Northern America | I42: 19 | J42: 21
A43: Cayman Islands | B43: KY | C43: CYM | D43: 136 | E43: ISO 3166-2:KY | F43: Americas | G43: Latin America and the Caribbean | H43: Caribbean | I43: 19 | J43: 419 | K43: 29
A44: Central African Republic | B44: CF | C44: CAF | D44: 140 | E44: ISO 3166-2:CF | F44: Africa | G44: Sub-Saharan Africa | H44: Middle Africa | I44: 2 | J44: 202 | K44: 17
A45: Chad | B45: TD | C45: TCD | D45: 148 | E45: ISO 3166-2:TD | F45: Africa | G45: Sub-Saharan Africa | H45: Middle Africa | I45: 2 | J45: 202 | K45: 17
A46: Chile | B46: CL | C46: CHL | D46: 152 | E46: ISO 3166-2:CL | F46: Americas | G46: Latin America and the Caribbean | H46: South America | I46: 19 | J46: 419 | K46: 5
A47: China | B47: CN | C47: CHN | D47: 156 | E47: ISO 3166-2:CN | F47: Asia | G47: Eastern Asia | I47: 142 | J47: 30
A48: Christmas Island | B48: CX | C48: CXR | D48: 162 | E48: ISO 3166-2:CX | F48: Oceania | G48: Australia and New Zealand | I48: 9 | J48: 53
A49: Cocos (Keeling) Islands | B49: CC | C49: CCK | D49: 166 | E49: ISO 3166-2:CC | F49: Oceania | G49: Australia and New Zealand | I49: 9 | J49: 53
A50: Colombia | B50: CO | C50: COL | D50: 170 | E50: ISO 3166-2:CO | F50: Americas | G50: Latin America and the Caribbean | H50: South America | I50: 19 | J50: 419 | K50: 5
A51: Comoros | B51: KM | C51: COM | D51: 174 | E51: ISO 3166-2:KM | F51: Africa | G51: Sub-Saharan Africa | H51: Eastern Africa | I51: 2 | J51: 202 | K51: 14
A52: Congo | B52: CG | C52: COG | D52: 178 | E52: ISO 3166-2:CG | F52: Africa | G52: Sub-Saharan Africa | H52: Middle Africa | I52: 2 | J52: 202 | K52: 17
A53: Congo, Democratic Republic of the | B53: CD | C53: COD | D53: 180 | E53: ISO 3166-2:CD | F53: Africa | G53: Sub-Saharan Africa | H53: Middle Africa | I53: 2 | J53: 202 | K53: 17
A54: Cook Islands | B54: CK | C54: COK | D54: 184 | E54: ISO 3166-2:CK | F54: Oceania | G54: Polynesia | I54: 9 | J54: 61
A55: Costa Rica | B55: CR | C55: CRI | D55: 188 | E55: ISO 3166-2:CR | F55: Americas | G55: Latin America and the Caribbean | H55: Central America | I55: 19 | J55: 419 | K55: 13
A56: Côte d'Ivoire | B56: CI | C56: CIV | D56: 384 | E56: ISO 3166-2:CI | F56: Africa | G56: Sub-Saharan Africa | H56: Western Africa | I56: 2 | J56: 202 | K56: 11
A57: Croatia | B57: HR | C57: HRV | D57: 191 | E57: ISO 3166-2:HR | F57: Europe | G57: Southern Europe | I57: 150 | J57: 39
A58: Cuba | B58: CU | C58: CUB | D58: 192 | E58: ISO 3166-2:CU | F58: Americas | G58: Latin America and the Caribbean | H58: Caribbean | I58: 19 | J58: 419 | K58: 29
A59: Curaçao | B59: CW | C59: CUW | D59: 531 | E59: ISO 3166-2:CW | F59: Americas | G59: Latin America and the Caribbean | H59: Caribbean | I59: 19 | J59: 419 | K59: 29
A60: Cyprus | B60: CY | C60: CYP | D60: 196 | E60: ISO 3166-2:CY | F60: Asia | G60: Western Asia | I60: 142 | J60: 145
A61: Czechia | B61: CZ | C61: CZE | D61: 203 | E61: ISO 3166-2:CZ | F61: Europe | G61: Eastern Europe | I61: 150 | J61: 151
A62: Denmark | B62: DK | C62: DNK | D62: 208 | E62: ISO 3166-2:DK | F62: Europe | G62: Northern Europe | I62: 150 | J62: 154
A63: Djibouti | B63: DJ | C63: DJI | D63: 262 | E63: ISO 3166-2:DJ | F63: Africa | G63: Sub-Saharan Africa | H63: Eastern Africa | I63: 2 | J63: 202 | K63: 14
A64: Dominica | B64: DM | C64: DMA | D64: 212 | E64: ISO 3166-2:DM | F64: Americas | G64: Latin America and the Caribbean | H64: Caribbean | I64: 19 | J64: 419 | K64: 29
A65: Dominican Republic | B65: DO | C65: DOM | D65: 214 | E65: ISO 3166-2:DO | F65: Americas | G65: Latin America and the Caribbean | H65: Caribbean | I65: 19 | J65: 419 | K65: 29
A66: Ecuador | B66: EC | C66: ECU | D66: 218 | E66: ISO 3166-2:EC | F66: Americas | G66: Latin America and the Caribbean | H66: South America | I66: 19 | J66: 419 | K66: 5
A67: Egypt | B67: EG | C67: EGY | D67: 818 | E67: ISO 3166-2:EG | F67: Africa | G67: Northern Africa | I67: 2 | J67: 15
A68: El Salvador | B68: SV | C68: SLV | D68: 222 | E68: ISO 3166-2:SV | F68: Americas | G68: Latin America and the Caribbean | H68: Central America | I68: 19 | J68: 419 | K68: 13
A69: Equatorial Guinea | B69: GQ | C69: GNQ | D69: 226 | E69: ISO 3166-2:GQ | F69: Africa | G69: Sub-Saharan Africa | H69: Middle Africa | I69: 2 | J69: 202 | K69: 17
A70: Eritrea | B70: ER | C70: ERI | D70: 232 | E70: ISO 3166-2:ER | F70: Africa | G70: Sub-Saharan Africa | H70: Eastern Africa | I70: 2 | J70: 202 | K70: 14
A71: Estonia | B71: EE | C71: EST | D71: 233 | E71: ISO 3166-2:EE | F71: Europe | G71: Northern Europe | I71: 150 | J71: 154
A72: Eswatini | B72: SZ | C72: SWZ | D72: 748 | E72: ISO 3166-2:SZ | F72: Africa | G72: Sub-Saharan Africa | H72: Southern Africa | I72: 2 | J72: 202 | K72: 18
A73: Ethiopia | B73: ET | C73: ETH | D73: 231 | E73: ISO 3166-2:ET | F73: Africa | G73: Sub-Saharan Africa | H73: Eastern Africa | I73: 2 | J73: 202 | K73: 14
A74: Falkland Islands (Malvinas) | B74: FK | C74: FLK | D74: 238 | E74: ISO 3166-2:FK | F74: Americas | G74: Latin America and the Caribbean | H74: South America | I74: 19 | J74: 419 | K74: 5
A75: Faroe Islands | B75: FO | C75: FRO | D75: 234 | E75: ISO 3166-2:FO | F75: Europe | G75: Northern Europe | I75: 150 | J75: 154
A76: Fiji | B76: FJ | C76: FJI | D76: 242 | E76: ISO 3166-2:FJ | F76: Oceania | G76: Melanesia | I76: 9 | J76: 54
A77: Finland | B77: FI | C77: FIN | D77: 246 | E77: ISO 3166-2:FI | F77: Europe | G77: Northern Europe | I77: 150 | J77: 154
A78: France | B78: FR | C78: FRA | D78: 250 | E78: ISO 3166-2:FR | F78: Europe | G78: Western Europe | I78: 150 | J78: 155
A79: French Guiana | B79: GF | C79: GUF | D79: 254 | E79: ISO 3166-2:GF | F79: Americas | G79: Latin America and the Caribbean | H79: South America | I79: 19 | J79: 419 | K79: 5
A80: French Polynesia | B80: PF | C80: PYF | D80: 258 | E80: ISO 3166-2:PF | F80: Oceania | G80: Polynesia | I80: 9 | J80: 61
A81: French Southern Territories | B81: TF | C81: ATF | D81: 260 | E81: ISO 3166-2:TF | F81: Africa | G81: Sub-Saharan Africa | H81: Eastern Africa | I81: 2 | J81: 202 | K81: 14
A82: Gabon | B82: GA | C82: GAB | D82: 266 | E82: ISO 3166-2:GA | F82: Africa | G82: Sub-Saharan Africa | H82: Middle Africa | I82: 2 | J82: 202 | K82: 17
A83: Gambia | B83: GM | C83: GMB | D83: 270 | E83: ISO 3166-2:GM | F83: Africa | G83: Sub-Saharan Africa | H83: Western Africa | I83: 2 | J83: 202 | K83: 11
A84: Georgia | B84: GE | C84: GEO | D84: 268 | E84: ISO 3166-2:GE | F84: Asia | G84: Western Asia | I84: 142 | J84: 145
A85: Germany | B85: DE | C85: DEU | D85: 276 | E85: ISO 3166-2:DE | F85: Europe | G85: Western Europe | I85: 150 | J85: 155
A86: Ghana | B86: GH | C86: GHA | D86: 288 | E86: ISO 3166-2:GH | F86: Africa | G86: Sub-Saharan Africa | H86: Western Africa | I86: 2 | J86: 202 | K86: 11
A87: Gibraltar | B87: GI | C87: GIB | D87: 292 | E87: ISO 3166-2:GI | F87: Europe | G87: Southern Europe | I87: 150 | J87: 39
A88: Greece | B88: GR | C88: GRC | D88: 300 | E88: ISO 3166-2:GR | F88: Europe | G88: Southern Europe | I88: 150 | J88: 39
A89: Greenland | B89: GL | C89: GRL | D89: 304 | E89: ISO 3166-2:GL | F89: Americas | G89: Northern America | I89: 19 | J89: 21
A90: Grenada | B90: GD | C90: GRD | D90: 308 | E90: ISO 3166-2:GD | F90: Americas | G90: Latin America and the Caribbean | H90: Caribbean | I90: 19 | J90: 419 | K90: 29
A91: Guadeloupe | B91: GP | C91: GLP | D91: 312 | E91: ISO 3166-2:GP | F91: Americas | G91: Latin America and the Caribbean | H91: Caribbean | I91: 19 | J91: 419 | K91: 29
A92: Guam | B92: GU | C92: GUM | D92: 316 | E92: ISO 3166-2:GU | F92: Oceania | G92: Micronesia | I92: 9 | J92: 57
A93: Guatemala | B93: GT | C93: GTM | D93: 320 | E93: ISO 3166-2:GT | F93: Americas | G93: Latin America and the Caribbean | H93: Central America | I93: 19 | J93: 419 | K93: 13
A94: Guernsey | B94: GG | C94: GGY | D94: 831 | E94: ISO 3166-2:GG | F94: Europe | G94: Northern Europe | I94: 150 | J94: 154
A95: Guinea | B95: GN | C95: GIN | D95: 324 | E95: ISO 3166-2:GN | F95: Africa | G95: Sub-Saharan Africa | H95: Western Africa | I95: 2 | J95: 202 | K95: 11
A96: Guinea-Bissau | B96: GW | C96: GNB | D96: 624 | E96: ISO 3166-2:GW | F96: Africa | G96: Sub-Saharan Africa | H96: Western Africa | I96: 2 | J96: 202 | K96: 11
A97: Guyana | B97: GY | C97: GUY | D97: 328 | E97: ISO 3166-2:GY | F97: Americas | G97: Latin America and the Caribbean | H97: South America | I97: 19 | J97: 419 | K97: 5
A98: Haiti | B98: HT | C98: HTI | D98: 332 | E98: ISO 3166-2:HT | F98: Americas | G98: Latin America and the Caribbean | H98: Caribbean | I98: 19 | J98: 419 | K98: 29
A99: Heard Island and McDonald Islands | B99: HM | C99: HMD | D99: 334 | E99: ISO 3166-2:HM | F99: Oceania | G99: Australia and New Zealand | I99: 9 | J99: 53
A100: Holy See | B100: VA | C100: VAT | D100: 336 | E100: ISO 3166-2:VA | F100: Europe | G100: Southern Europe | I100: 150 | J100: 39
...

Sheet matches
A1: Column1 | B1: original | C1: matched
A2: 0 | B2: Afghanistan | C2: Afghanistan
A3: 1 | B3: Albania | C3: Albania
A4: 2 | B4: Algeria | C4: Algeria
A5: 3 | B5: American Samoa | C5: American Samoa
A6: 4 | B6: Andorra | C6: Andorra
A7: 5 | B7: Angola | C7: Angola
A8: 6 | B8: Antigua and Barbuda | C8: Antigua and Barbuda
A9: 7 | B9: Argentina | C9: Argentina
A10: 8 | B10: Armenia | C10: Armenia
A11: 9 | B11: Aruba | C11: Aruba
A12: 10 | B12: Australia | C12: Australia
A13: 11 | B13: Austria | C13: Austria
... A218: 216 | B218: Zimbabwe | C218: Zimbabwe

Sheet Sheet1
A1: Country name | B1: Match | C1: Region | D1: Population, total [SP.POP.TOTL] | E1: Surface area (sq. km) [AG.SRF.TOTL.K2] | F1: Life expectancy at birth, total (years) [SP.DYN.LE00.IN] | G1: GDP (current US$) [NY.GDP.MKTP.CD] | H1: Mobile cellular subscriptions (per 100 people) [IT.CEL.SETS.P2] | I1: GDP per capita (current US$) [NY.GDP.PCAP.CD]
A2: Afghanistan | B2: Afghanistan | C2: =_xlfn.XLOOKUP(B2,'regions'!A:A,'regions'!F:F) -> Asia | D2: 40578842 | E2: 652860 | F2: 65.617 | G2: 1.4497244e+10 | H2: 56.2655 | I2: 357.26115
A3: Albania | B3: Albania | C3: =_xlfn.XLOOKUP(B3,'regions'!A:A,'regions'!F:F) -> Europe | D3: 2451636 | E3: 28750 | F3: 78.769 | G3: 1.9017247e+10 | H3: 98.395 | I3: 7756.9619
A4: Algeria | B4: Algeria | C4: =_xlfn.XLOOKUP(B4,'regions'!A:A,'regions'!F:F) -> Africa | D4: 45477389 | E4: 2381740 | F4: 76.129 | G4: 2.2558164e+11 | H4: 107.787 | I4: 4960.3033
A5: American Samoa | B5: American Samoa | C5: =_xlfn.XLOOKUP(B5,'regions'!A:A,'regions'!F:F) -> Oceania | D5: 48342 | E5: 200 | F5: 72.752 | G5: 871000000 | I5: 18017.459
A6: Andorra | B6: Andorra | C6: =_xlfn.XLOOKUP(B6,'regions'!A:A,'regions'!F:F) -> Europe | D6: 79705 | E6: 470 | F6: 84.016 | G6: 3.3806117e+09 | H6: 142.426 | I6: 42414.048
A7: Angola | B7: Angola | C7: =_xlfn.XLOOKUP(B7,'regions'!A:A,'regions'!F:F) -> Africa | D7: 35635029 | E7: 1246700 | F7: 64.246 | G7: 1.3121221e+11 | H7: 66.6008 | I7: 3682.1132
A8: Antigua and Barbuda | B8: Antigua and Barbuda | C8: =_xlfn.XLOOKUP(B8,'regions'!A:A,'regions'!F:F) -> Americas | D8: 92840 | E8: 440 | F8: 77.483 | G8: 1.8665667e+09 | H8: 200.541 | I8: 20105.199
A9: Argentina | B9: Argentina | C9: =_xlfn.XLOOKUP(B9,'regions'!A:A,'regions'!F:F) -> Americas | D9: 45407904 | E9: 2780400 | F9: 75.806 | G9: 6.3399376e+11 | H9: 131.484 | I9: 13962.189
A10: Armenia | B10: Armenia | C10: =_xlfn.XLOOKUP(B10,'regions'!A:A,'regions'!F:F) -> Asia | D10: 2969200 | E10: 29740 | F10: 74.765854 | G10: 1.9513507e+10 | H10: 130.54 | I10: 6571.9745
A11: Aruba | B11: Aruba | C11: =_xlfn.XLOOKUP(B11,'regions'!A:A,'regions'!F:F) -> Americas | D11: 107310 | E11: 180 | F11: 76.226 | G11: 3.3240344e+09 | H11: 130.648 | I11: 30975.999
A12: Australia | B12: Australia | C12: =_xlfn.XLOOKUP(B12,'regions'!A:A,'regions'!F:F) -> Oceania | D12: 26018721 | E12: 7741220 | F12: 83.2 | G12: 1.6956275e+12 | H12: 109.469 | I12: 65169.519
A13: Austria | B13: Austria | C13: =_xlfn.XLOOKUP(B13,'regions'!A:A,'regions'!F:F) -> Europe | D13: 9041851 | E13: 83879 | F13: 81.295122 | G13: 4.732213e+11 | H13: 121.166 | I13: 52336.773
A14: Azerbaijan | B14: Azerbaijan | C14: =_xlfn.XLOOKUP(B14,'regions'!A:A,'regions'!F:F) -> Asia | D14: 10141756 | E14: 86600 | F14: 74.125 | G14: 7.8807471e+10 | H14: 107.506 | I14: 7770.5942
A15: Bahamas, The | B15: Bahamas | C15: =_xlfn.XLOOKUP(B15,'regions'!A:A,'regions'!F:F) -> Americas | D15: 397538 | E15: 13880 | F15: 74.491 | G15: 13896800000 | H15: 101.624 | I15: 34957.161
A16: Bahrain | B16: Bahrain | C16: =_xlfn.XLOOKUP(B16,'regions'!A:A,'regions'!F:F) -> Asia | D16: 1524693 | E16: 790 | F16: 80.992 | G16: 4.6458191e+10 | H16: 139.636 | I16: 30470.522
A17: Bangladesh | B17: Bangladesh | C17: =_xlfn.XLOOKUP(B17,'regions'!A:A,'regions'!F:F) -> Asia | D17: 169384897 | E17: 147570 | F17: 74.265 | G17: 4.6013169e+11 | H17: 109.867 | I17: 2716.4859
... A28: Brazil | B28: Brazil | C28: =_xlfn.XLOOKUP(B28,'regions'!A:A,'regions'!F:F) -> Americas | D28: 210306415 | E28: 8510420 | F28: 74.872 | G28: 1.9519238e+12 | H28: 101.245 | I28: 9281.3328
A29: British Virgin Islands | B29: Virgin Islands (British) | C29: =_xlfn.XLOOKUP(B29,'regions'!A:A,'regions'!F:F) -> Americas | D29: 38319 | E29: 150 | F29: 77.177 | H29: 92.8913
A30: Brunei Darussalam | B30: Brunei Darussalam | C30: =_xlfn.XLOOKUP(B30,'regions'!A:A,'regions'!F:F) -> Asia | D30: 455370 | E30: 5770 | F30: 72.917 | G30: 1.6681536e+10 | H30: 116.108 | I30: 36632.928
A31: Bulgaria | B31: Bulgaria | C31: =_xlfn.XLOOKUP(B31,'regions'!A:A,'regions'!F:F) -> Europe | D31: 6465097 | E31: 111000 | F31: 74.160976 | G31: 9.0506153e+10 | H31: 116.679 | I31: 13999.195
A32: Burkina Faso | B32: Burkina Faso | C32: =_xlfn.XLOOKUP(B32,'regions'!A:A,'regions'!F:F) -> Africa | D32: 22509038 | E32: 274200 | F32: 60.7 | G32: 1.8622421e+10 | H32: 119.463 | I32: 827.33084
A33: Burundi | B33: Burundi | C33: =_xlfn.XLOOKUP(B33,'regions'!A:A,'regions'!F:F) -> Africa | D33: 13321097 | E33: 27830 | F33: 62.882 | G33: 4.0361926e+09 | H33: 56.26 | I33: 302.99251
A34: Cabo Verde | B34: Cabo Verde | C34: =_xlfn.XLOOKUP(B34,'regions'!A:A,'regions'!F:F) -> Africa | D34: 519741 | E34: 4030 | F34: 75.907 | G34: 2.2470033e+09 | H34: 113.247 | I34: 4323.3136
A35: Cambodia | B35: Cambodia | C35: =_xlfn.XLOOKUP(B35,'regions'!A:A,'regions'!F:F) -> Asia | D35: 17201724 | E35: 181040 | F35: 70.528 | G35: 3.9994533e+10 | H35: 113.392 | I35: 2325.0305
A36: Cameroon | B36: Cameroon | C36: =_xlfn.XLOOKUP(B36,'regions'!A:A,'regions'!F:F) -> Africa | D36: 27632771 | E36: 475440 | F36: 62.443 | G36: 4.4347206e+10 | H36: 89.8274 | I36: 1604.8773
A37: Canada | B37: Canada | C37: =_xlfn.XLOOKUP(B37,'regions'!A:A,'regions'!F:F) -> Americas | D37: 38935934 | E37: 15634410 | F37: 81.245366 | G37: 2.1904111e+12 | H37: 91.2387 | I37: 56256.801
A38: Cayman Islands | B38: Cayman Islands | C38: =_xlfn.XLOOKUP(B38,'regions'!A:A,'regions'!F:F) -> Americas | D38: 71591 | E38: 264 | F38: 79.984 | G38: 6.6601612e+09 | H38: 139.315 | I38: 93030.705
A39: Central African Republic | B39: Central African Republic | C39: =_xlfn.XLOOKUP(B39,'regions'!A:A,'regions'!F:F) -> Africa | D39: 5098039 | E39: 622980 | F39: 18.818 | G39: 2.3826186e+09 | H39: 38.8218 | I39: 467.35983
A40: Chad | B40: Chad | C40: =_xlfn.XLOOKUP(B40,'regions'!A:A,'regions'!F:F) -> Africa | D40: 18455316 | E40: 1284000 | F40: 54.528 | G40: 1.7828508e+10 | H40: 65.4378 | I40: 966.03647
A41: Channel Islands | B41: Cocos (Keeling) Islands | C41: =_xlfn.XLOOKUP(B41,'regions'!A:A,'regions'!F:F) -> Oceania | D41: 167215 | F41: 81 | G41: 1.1308273e+10 | I41: 67627.142
A42: Chile | B42: Chile | C42: =_xlfn.XLOOKUP(B42,'regions'!A:A,'regions'!F:F) -> Americas | D42: 19553036 | E42: 757244.88 | F42: 79.176 | G42: 3.0122658e+11 | H42: 135.114 | I42: 15405.617
A43: China | B43: China | C43: =_xlfn.XLOOKUP(B43,'regions'!A:A,'regions'!F:F) -> Asia | D43: 1412175000 | E43: 9562910 | F43: 78.202 | G43: 1.8316765e+13 | H43: 124.195 | I43: 12970.606
A44: Colombia | B44: Colombia | C44: =_xlfn.XLOOKUP(B44,'regions'!A:A,'regions'!F:F) -> Americas | D44: 51737944 | E44: 1140619.1 | F44: 76.508 | G44: 3.4563249e+11 | H44: 156.195 | I44: 6680.4451
A45: Comoros | B45: Comoros | C45: =_xlfn.XLOOKUP(B45,'regions'!A:A,'regions'!F:F) -> Africa | D45: 834188 | E45: 1861 | F45: 66.481 | G45: 1.2224855e+09 | H45: 100.549 | I45: 1465.4796
A46: Congo, Dem. Rep. | B46: Congo | C46: =_xlfn.XLOOKUP(B46,'regions'!A:A,'regions'!F:F) -> Africa | D46: 102396968 | E46: 2344860 | F46: 60.979 | G46: 7.0422346e+10 | H46: 48.6774 | I46: 687.73859
A47: Congo, Rep. | B47: Congo | C47: =_xlfn.XLOOKUP(B47,'regions'!A:A,'regions'!F:F) -> Africa | D47: 6035104 | E47: 342000 | F47: 65 | G47: 1.581703e+10 | H47: 93.6259 | I47: 2620.838
A48: Costa Rica | B48: Costa Rica | C48: =_xlfn.XLOOKUP(B48,'regions'!A:A,'regions'!F:F) -> Americas | D48: 5081765 | E48: 51100 | F48: 79.316 | G48: 6.9243626e+10 | H48: 154.989 | I48: 13625.901
A49: Cote d'Ivoire | B49: Côte d'Ivoire | C49: =_xlfn.XLOOKUP(B49,'regions'!A:A,'regions'!F:F) -> Africa | D49: 30395002 | E49: 322460 | F49: 61.562 | G49: 7.0922825e+10 | H49: 161.232 | I49: 2333.3713
A50: Croatia | B50: Croatia | C50: =_xlfn.XLOOKUP(B50,'regions'!A:A,'regions'!F:F) -> Europe | D50: 3855641 | E50: 88070 | F50: 77.57561 | G50: 7.1196499e+10 | H50: 114.677 | I50: 18465.541
A51: Cuba | B51: Cuba | C51: =_xlfn.XLOOKUP(B51,'regions'!A:A,'regions'!F:F) -> Americas | D51: 11059820 | E51: 109880 | F51: 77.629 | H51: 68.718
A52: Curacao | B52: Curaçao | C52: =_xlfn.XLOOKUP(B52,'regions'!A:A,'regions'!F:F) -> Americas | D52: 153321 | E52: 444 | F52: 76.729 | G52: 3.0751808e+09 | H52: 92.7325 | I52: 20057.14
A53: Cyprus | B53: Cyprus | C53: =_xlfn.XLOOKUP(B53,'regions'!A:A,'regions'!F:F) -> Asia | D53: 1331370 | E53: 9250 | F53: 80.434 | G53: 3.1218039e+10 | H53: 151.241 | I53: 33231.043
A54: Czechia | B54: Czechia | C54: =_xlfn.XLOOKUP(B54,'regions'!A:A,'regions'!F:F) -> Europe | D54: 10672118 | E54: 78871.47 | F54: 78.929268 | G54: 3.0183123e+11 | H54: 128.105 | I54: 28282.224
A55: Denmark | B55: Denmark | C55: =_xlfn.XLOOKUP(B55,'regions'!A:A,'regions'!F:F) -> Europe | D55: 5903037 | E55: 42920 | F55: 81.304878 | G55: 4.0011431e+11 | H55: 126.484 | I55: 67781.094
A56: Djibouti | B56: Djibouti | C56: =_xlfn.XLOOKUP(B56,'regions'!A:A,'regions'!F:F) -> Africa | D56: 1137096 | E56: 23200 | F56: 65.54 | G56: 3.5628149e+09 | H56: 46.7771 | I56: 3133.2578
A57: Dominica | B57: Dominica | C57: =_xlfn.XLOOKUP(B57,'regions'!A:A,'regions'!F:F) -> Americas | D57: 66826 | E57: 750 | F57: 71.081 | G57: 6.2306296e+08 | H57: 85.1899 | I57: 9323.6609
A58: Dominican Republic | B58: Dominican Republic | C58: =_xlfn.XLOOKUP(B58,'regions'!A:A,'regions'!F:F) -> Americas | D58: 11230734 | E58: 146839.46 | F58: 74.211 | G58: 1.1347809e+11 | H58: 90.376 | I58: 10104.245
A59: Ecuador | B59: Ecuador | C59: =_xlfn.XLOOKUP(B59,'regions'!A:A,'regions'!F:F) -> Americas | D59: 17823897 | E59: 256370 | F59: 76.577 | G59: 116133121000 | H59: 98.1309 | I59: 6515.5853
A60: Egypt, Arab Rep. | B60: Egypt | C60: =_xlfn.XLOOKUP(B60,'regions'!A:A,'regions'!F:F) -> Africa | D60: 112618250 | E60: 1001450 | F60: 71.01 | G60: 4.7674772e+11 | H60: 90.6795 | I60: 4233.3078
A61: El Salvador | B61: El Salvador | C61: =_xlfn.XLOOKUP(B61,'regions'!A:A,'regions'!F:F) -> Americas | D61: 6280319 | E61: 21040 | F61: 71.969 | G61: 31870120000 | H61: 183.249 | I61: 5074.6021
A62: Equatorial Guinea | B62: Equatorial Guinea | C62: =_xlfn.XLOOKUP(B62,'regions'!A:A,'regions'!F:F) -> Africa | D62: 1803545 | E62: 28050 | F62: 63.355 | G62: 1.3687643e+10 | H62: 49.538 | I62: 7589.2996
A63: Eritrea | B63: Eritrea | C63: =_xlfn.XLOOKUP(B63,'regions'!A:A,'regions'!F:F) -> Africa | D63: 3409447 | E63: 121765.8 | F63: 67.789 | H63: 59.1248
A64: Estonia | B64: Estonia | C64: =_xlfn.XLOOKUP(B64,'regions'!A:A,'regions'!F:F) -> Europe | D64: 1348840 | E64: 45340 | F64: 77.843902 | G64: 3.8226642e+10 | H64: 152.271 | I64: 28340.383
A65: Eswatini | B65: Eswatini | C65: =_xlfn.XLOOKUP(B65,'regions'!A:A,'regions'!F:F) -> Africa | D65: 1218917 | E65: 17360 | F65: 63.028 | G65: 4.7466603e+09 | H65: 121.492 | I65: 3894.162
A66: Ethiopia | B66: Ethiopia | C66: =_xlfn.XLOOKUP(B66,'regions'!A:A,'regions'!F:F) -> Africa | D66: 125384287 | E66: 1136239.7 | F66: 66.897 | G66: 123140304666 | H66: 56.9643 | I66: 982.10316
A67: Faroe Islands | B67: Faroe Islands | C67: =_xlfn.XLOOKUP(B67,'regions'!A:A,'regions'!F:F) -> Europe | D67: 53912 | E67: 12960 | F67: 82.943902 | G67: 3.6152418e+09 | H67: 105.804 | I67: 67058.202
A68: Fiji | B68: Fiji | C68: =_xlfn.XLOOKUP(B68,'regions'!A:A,'regions'!F:F) -> Oceania | D68: 919422 | E68: 18270 | F68: 67.148 | G68: 4.9778619e+09 | H68: 111.749 | I68: 5414.1209
A69: Finland | B69: Finland | C69: =_xlfn.XLOOKUP(B69,'regions'!A:A,'regions'!F:F) -> Europe | D69: 5556106 | E69: 338470 | F69: 81.187805 | G69: 2.802531e+11 | H69: 128.023 | I69: 50440.56
A70: France | B70: France | C70: =_xlfn.XLOOKUP(B70,'regions'!A:A,'regions'!F:F) -> Europe | D70: 68184457 | E70: 606410 | F70: 82.129268 | G70: 2.7947881e+12 | H70: 115.951 | I70: 40988.64
A71: French Polynesia | B71: French Polynesia | C71: =_xlfn.XLOOKUP(B71,'regions'!A:A,'regions'!F:F) -> Oceania | D71: 280378 | E71: 3471 | F71: 83.859 | G71: 5.6226883e+09 | H71: 116.866 | I71: 20053.957
A72: Gabon | B72: Gabon | C72: =_xlfn.XLOOKUP(B72,'regions'!A:A,'regions'!F:F) -> Africa | D72: 2430747 | E72: 267670 | F72: 67.713 | G72: 2.0440656e+10 | H72: 123.233 | I72: 8409.2074
A73: Gambia, The | B73: Gambia | C73: =_xlfn.XLOOKUP(B73,'regions'!A:A,'regions'!F:F) -> Africa | D73: 2636470 | E73: 11300 | F73: 64.859 | G73: 2.2047345e+09 | H73: 106.782 | I73: 836.24488
A74: Georgia | B74: Georgia | C74: =_xlfn.XLOOKUP(B74,'regions'!A:A,'regions'!F:F) -> Asia | D74: 3712502 | E74: 69700 | F74: 74.141 | G74: 2.4984569e+10 | H74: 154.014 | I74: 6729.8466
A75: Germany | B75: Germany | C75: =_xlfn.XLOOKUP(B75,'regions'!A:A,'regions'!F:F) -> Europe | D75: 83177813 | E75: 357600 | F75: 80.608049 | G75: 4.2010217e+12 | H75: 124.158 | I75: 50506.518
A76: Ghana | B76: Ghana | C76: =_xlfn.XLOOKUP(B76,'regions'!A:A,'regions'!F:F) -> Africa | D76: 33149152 | E76: 238533 | F76: 65.246 | G76: 7.3919003e+10 | H76: 120.803 | I76: 2229.8912
A77: Gibraltar | B77: Gibraltar | C77: =_xlfn.XLOOKUP(B77,'regions'!A:A,'regions'!F:F) -> Europe | D77: 37609 | E77: 10 | F77: 83.517 | H77: 97.6043
A78: Greece | B78: Greece | C78: =_xlfn.XLOOKUP(B78,'regions'!A:A,'regions'!F:F) -> Europe | D78: 10436882 | E78: 131960 | F78: 80.787805 | G78: 2.1799019e+11 | H78: 109.027 | I78: 20886.524
A79: Greenland | B79: Greenland | C79: =_xlfn.XLOOKUP(B79,'regions'!A:A,'regions'!F:F) -> Americas | D79: 56661 | E79: 410450 | F79: 71.540488 | G79: 3.1523348e+09 | H79: 118.637 | I79: 55635.001
A80: Grenada | B80: Grenada | C80: =_xlfn.XLOOKUP(B80,'regions'!A:A,'regions'!F:F) -> Americas | D80: 116913 | E80: 340 | F80: 75.151 | G80: 1.2240074e+09 | H80: 95.7592 | I80: 10469.387
A81: Guam | B81: Guam | C81: =_xlfn.XLOOKUP(B81,'regions'!A:A,'regions'!F:F) -> Oceania | D81: 165180 | E81: 540 | F81: 77.102 | G81: 6910000000 | I81: 41833.152
A82: Guatemala | B82: Guatemala | C82: =_xlfn.XLOOKUP(B82,'regions'!A:A,'regions'!F:F) -> Americas | D82: 17847877 | E82: 108890 | F82: 71.206 | G82: 9.5641447e+10 | H82: 115.156 | I82: 5358.7016
A83: Guinea | B83: Guinea | C83: =_xlfn.XLOOKUP(B83,'regions'!A:A,'regions'!F:F) -> Africa | D83: 14055137 | E83: 245860 | F83: 60.432 | G83: 1.9910453e+10 | H83: 108.885 | I83: 1416.5961
A84: Guinea-Bissau | B84: Guinea-Bissau | C84: =_xlfn.XLOOKUP(B84,'regions'!A:A,'regions'!F:F) -> Africa | D84: 2105529 | E84: 36130 | F84: 63.605 | G84: 1.8596014e+09 | H84: 125.935 | I84: 883.19913
A85: Guyana | B85: Guyana | C85: =_xlfn.XLOOKUP(B85,'regions'!A:A,'regions'!F:F) -> Americas | D85: 821637 | E85: 214970 | F85: 69.888 | G85: 1.4718388e+10 | H85: 112.565 | I85: 17913.493
A86: Haiti | B86: Haiti | C86: =_xlfn.XLOOKUP(B86,'regions'!A:A,'regions'!F:F) -> Americas | D86: 11503606 | E86: 27750 | F86: 63.948 | G86: 2.0253552e+10 | H86: 65.1889 | I86: 1760.6264
A87: Honduras | B87: Honduras | C87: =_xlfn.XLOOKUP(B87,'regions'!A:A,'regions'!F:F) -> Americas | D87: 10463872 | E87: 112490 | F87: 72.715 | G87: 3.1426042e+10 | H87: 75.8551 | I87: 3003.29
A88: Hong Kong SAR, China | B88: China | C88: =_xlfn.XLOOKUP(B88,'regions'!A:A,'regions'!F:F) -> Asia | D88: 7346100 | E88: 1110 | F88: 83.660976 | G88: 3.5867953e+11 | H88: 292.808 | I88: 48825.844
A89: Hungary | B89: Hungary | C89: =_xlfn.XLOOKUP(B89,'regions'!A:A,'regions'!F:F) -> Europe | D89: 9605074 | E89: 93030 | F89: 75.868293 | G89: 1.7700258e+11 | H89: 105.794 | I89: 18428.029
A90: Iceland | B90: Iceland | C90: =_xlfn.XLOOKUP(B90,'regions'!A:A,'regions'!F:F) -> Europe | D90: 382003 | E90: 103000 | F90: 82.119512 | G90: 2.9166103e+10 | H90: 120.115 | I90: 76350.455
A91: India | B91: India | C91: =_xlfn.XLOOKUP(B91,'regions'!A:A,'regions'!F:F) -> Asia | D91: 1425423212 | E91: 3287260 | F91: 71.698 | G91: 3.3461073e+12 | H91: 80.1818 | I91: 2347.4483
A92: Indonesia | B92: Indonesia | C92: =_xlfn.XLOOKUP(B92,'regions'!A:A,'regions'!F:F) -> Asia | D92: 278830529 | E92: 1916906.8 | F92: 70.925 | G92: 1.3191012e+12 | H92: 122.873 | I92: 4730.8348
A93: Iran, Islamic Rep. | B93: Iran, Islamic Republic of | C93: =_xlfn.XLOOKUP(B93,'regions'!A:A,'regions'!F:F) -> Asia | D93: 89524246 | E93: 1745150 | F93: 76.799 | G93: 4.2266226e+11 | H93: 162.713 | I93: 4721.2044
... A95: Ireland | B95: Ireland | C95: =_xlfn.XLOOKUP(B95,'regions'!A:A,'regions'!F:F) -> Europe | D95: 5212836 | E95: 70280 | F95: 82.509756 | G95: 5.4834179e+11 | H95: 110.609 | I95: 105190.69
A96: Isle of Man | B96: Isle of Man | C96: =_xlfn.XLOOKUP(B96,'regions'!A:A,'regions'!F:F) -> Europe | D96: 84132 | E96: 570 | F96: 80.956 | G96: 7.4312574e+09 | I96: 88328.548
A97: Israel | B97: Israel | C97: =_xlfn.XLOOKUP(B97,'regions'!A:A,'regions'!F:F) -> Asia | D97: 9557500 | E97: 22070 | F97: 82.7 | G97: 5.2518101e+11 | H97: 151.138 | I97: 54949.622
A98: Italy | B98: Italy | C98: =_xlfn.XLOOKUP(B98,'regions'!A:A,'regions'!F:F) -> Europe | D98: 59013667 | E98: 302070 | F98: 82.7 | G98: 2.1040676e+12 | H98: 131.674 | I98: 35653.904
A99: Jamaica | B99: Jamaica | C99: =_xlfn.XLOOKUP(B99,'regions'!A:A,'regions'!F:F) -> Americas | D99: 2839144 | E99: 10990 | F99: 71.481 | G99: 1.8813517e+10 | H99: 105.762 | I99: 6626.475
A100: Japan | B100: Japan | C100: =_xlfn.XLOOKUP(B100,'regions'!A:A,'regions'!F:F) -> Asia | D100: 125124989 | E100: 377969.27 | F100: 83.996341 | G100: 4.2624633e+12 | H100: 168.603 | I100: 34065.644
A101: Jordan | B101: Jordan | C101: =_xlfn.XLOOKUP(B101,'regions'!A:A,'regions'!F:F) -> Asia | D101: 11256263 | E101: 89318 | F101: 77.088 | G101: 4.8764963e+10 | H101: 67.7457 | I101: 4332.2516
A102: Kazakhstan | B102: Kazakhstan | C102: =_xlfn.XLOOKUP(B102,'regions'!A:A,'regions'!F:F) -> Asia | D102: 20034609 | E102: 2724902 | F102: 73.503 | G102: 2.2549633e+11 | H102: 125.642 | I102: 11255.34
A103: Kenya | B103: Kenya | C103: =_xlfn.XLOOKUP(B103,'regions'!A:A,'regions'!F:F) -> Africa | D103: 54252461 | E103: 591969 | F103: 63.549 | G103: 1.1444898e+11 | H103: 121.169 | I103: 2109.5629
A104: Kiribati | B104: Kiribati | C104: =_xlfn.XLOOKUP(B104,'regions'!A:A,'regions'!F:F) -> Oceania | D104: 130469 | E104: 810 | F104: 66.269 | G104: 2.7004045e+08 | H104: 49.112 | I104: 2069.7672
A105: Korea, Dem. People's Rep. | B105: Korea, Democratic People's Republic of | C105: =_xlfn.XLOOKUP(B105,'regions'!A:A,'regions'!F:F) -> Asia | D105: 26328845 | E105: 120540 | F105: 73.641 | H105: 24.1311
A106: Korea, Rep. | B106: Korea, Republic of | C106: =_xlfn.XLOOKUP(B106,'regions'!A:A,'regions'!F:F) -> Asia | D106: 51672569 | E106: 100440 | F106: 82.680488 | G106: 1.7993631e+12 | H106: 148.684 | I106: 34822.405
A107: Kosovo | B107: Solomon Islands | C107: =_xlfn.XLOOKUP(B107,'regions'!A:A,'regions'!F:F) -> Oceania | D107: 1768096 | F107: 77.623 | G107: 9.3549076e+09 | H107: 34.5402 | I107: 5290.9501
A108: Kuwait | B108: Kuwait | C108: =_xlfn.XLOOKUP(B108,'regions'!A:A,'regions'!F:F) -> Asia | D108: 4589643 | E108: 17820 | F108: 80.587805 | G108: 1.8350205e+11 | H108: 168.35 | I108: 39981.769
A109: Kyrgyz Republic | B109: Central African Republic | C109: =_xlfn.XLOOKUP(B109,'regions'!A:A,'regions'!F:F) -> Africa | D109: 6975220 | E109: 199950 | F109: 72.04878 | G109: 1.2134931e+10 | H109: 106.926 | I109: 1739.7202
A110: Lao PDR | B110: Lao People's Democratic Republic | C110: =_xlfn.XLOOKUP(B110,'regions'!A:A,'regions'!F:F) -> Asia | D110: 7559007 | E110: 236800 | F110: 68.715 | G110: 1.5468785e+10 | H110: 63.3546 | I110: 2046.4044
A111: Latvia | B111: Latvia | C111: =_xlfn.XLOOKUP(B111,'regions'!A:A,'regions'!F:F) -> Europe | D111: 1879383 | E111: 64590 | F111: 74.278049 | G111: 3.8003199e+10 | H111: 115.203 | I111: 20221.104
...
